[
  {
    "author": "LMB Studio",
    "link_thumb": "https://live.staticflickr.com/65535/51786389297_756a6d49a2_o.gif",
    "link_bin": "https://github.com/lmbstudiocontact/mb5_3/raw/main/Boy_L6_1992492308.bin",
    "id_bin": "Boy_L6_1992492308",
    "list_language": [
      {
        "author": "LMB Studio",
        "link_thumb": "https://live.staticflickr.com/65535/51787829639_76003bcdf1_o.gif",
        "link_bin": "https://github.com/lmbstudiocontact/mb5_3/raw/main/Boy_L6_1992492308_English.bin",
        "name_language": "English",
        "id_bin_language": "Boy_L6_1992492308_English"
      },
      {
        "author": "LMB Studio",
        "link_thumb": "https://live.staticflickr.com/65535/51787456608_aaa586bcf6_o.gif",
        "link_bin": "https://github.com/lmbstudiocontact/mb5_3/raw/main/Boy_L6_1992492308_Portuguese.bin",
        "name_language": "Portuguese",
        "id_bin_language": "Boy_L6_1992492308_Portuguese"
      },
      {
        "author": "LMB Studio",
        "link_thumb": "https://live.staticflickr.com/65535/51787829514_5c47f4239a_o.gif",
        "link_bin": "https://github.com/lmbstudiocontact/mb5_3/raw/main/Boy_L6_1992492308_Russian.bin",
        "name_language": "Russian",
        "id_bin_language": "Boy_L6_1992492308_Russian"
      },
      {
        "author": "LMB Studio",
        "link_thumb": "https://live.staticflickr.com/65535/51787456498_da1ac8df01_o.gif",
        "link_bin": "https://github.com/lmbstudiocontact/mb5_3/raw/main/Boy_L6_1992492308_Spanish.bin",
        "name_language": "Spanish",
        "id_bin_language": "Boy_L6_1992492308_Spanish"
      }
    ],
    "array_tags": [
      "lmbstudio"
    ],
    "list_album": [
      {
        "id_album": "1995733213",
        "link_thumb": "https://live.staticflickr.com/65535/51786389297_756a6d49a2_o.gif",
        "title": "Boy_L6"
      }
    ]
  },
  {
    "author": "LMB Studio",
    "link_thumb": "https://live.staticflickr.com/65535/51787207221_3bafc50f78_o.gif",
    "link_bin": "https://github.com/lmbstudiocontact/mb5_3/raw/main/Boy_L6_1992492340.bin",
    "id_bin": "Boy_L6_1992492340",
    "list_language": [
      {
        "author": "LMB Studio",
        "link_thumb": "https://live.staticflickr.com/65535/51788078645_3ee1332f5d_o.gif",
        "link_bin": "https://github.com/lmbstudiocontact/mb5_3/raw/main/Boy_L6_1992492340_English.bin",
        "name_language": "English",
        "id_bin_language": "Boy_L6_1992492340_English"
      },
      {
        "author": "LMB Studio",
        "link_thumb": "https://live.staticflickr.com/65535/51787207126_a44e3a6848_o.gif",
        "link_bin": "https://github.com/lmbstudiocontact/mb5_3/raw/main/Boy_L6_1992492340_Portuguese.bin",
        "name_language": "Portuguese",
        "id_bin_language": "Boy_L6_1992492340_Portuguese"
      },
      {
        "author": "LMB Studio",
        "link_thumb": "https://live.staticflickr.com/65535/51788078555_b4a804f691_o.gif",
        "link_bin": "https://github.com/lmbstudiocontact/mb5_3/raw/main/Boy_L6_1992492340_Russian.bin",
        "name_language": "Russian",
        "id_bin_language": "Boy_L6_1992492340_Russian"
      },
      {
        "author": "LMB Studio",
        "link_thumb": "https://live.staticflickr.com/65535/51787456233_e39064ee2b_o.gif",
        "link_bin": "https://github.com/lmbstudiocontact/mb5_3/raw/main/Boy_L6_1992492340_Spanish.bin",
        "name_language": "Spanish",
        "id_bin_language": "Boy_L6_1992492340_Spanish"
      }
    ],
    "array_tags": [
      "lmbstudio"
    ],
    "list_album": [
      {
        "id_album": "1995733213",
        "link_thumb": "https://live.staticflickr.com/65535/51787207221_3bafc50f78_o.gif",
        "title": "Boy_L6"
      }
    ]
  },
  {
    "author": "LMB Studio",
    "link_thumb": "https://live.staticflickr.com/65535/51787829139_8ebf96f228_o.gif",
    "link_bin": "https://github.com/lmbstudiocontact/mb5_3/raw/main/Boy_L6_1992515313.bin",
    "id_bin": "Boy_L6_1992515313",
    "list_language": [
      {
        "author": "LMB Studio",
        "link_thumb": "https://live.staticflickr.com/65535/51787206906_05798e3c57_o.gif",
        "link_bin": "https://github.com/lmbstudiocontact/mb5_3/raw/main/Boy_L6_1992515313_English.bin",
        "name_language": "English",
        "id_bin_language": "Boy_L6_1992515313_English"
      },
      {
        "author": "LMB Studio",
        "link_thumb": "https://live.staticflickr.com/65535/51786388672_0148588c31_o.gif",
        "link_bin": "https://github.com/lmbstudiocontact/mb5_3/raw/main/Boy_L6_1992515313_Portuguese.bin",
        "name_language": "Portuguese",
        "id_bin_language": "Boy_L6_1992515313_Portuguese"
      },
      {
        "author": "LMB Studio",
        "link_thumb": "https://live.staticflickr.com/65535/51787456083_b9175e0874_o.gif",
        "link_bin": "https://github.com/lmbstudiocontact/mb5_3/raw/main/Boy_L6_1992515313_Russian.bin",
        "name_language": "Russian",
        "id_bin_language": "Boy_L6_1992515313_Russian"
      },
      {
        "author": "LMB Studio",
        "link_thumb": "https://live.staticflickr.com/65535/51786388602_b3d71a5280_o.gif",
        "link_bin": "https://github.com/lmbstudiocontact/mb5_3/raw/main/Boy_L6_1992515313_Spanish.bin",
        "name_language": "Spanish",
        "id_bin_language": "Boy_L6_1992515313_Spanish"
      }
    ],
    "array_tags": [
      "lmbstudio"
    ],
    "list_album": [
      {
        "id_album": "1995733213",
        "link_thumb": "https://live.staticflickr.com/65535/51787829139_8ebf96f228_o.gif",
        "title": "Boy_L6"
      }
    ]
  },
  {
    "author": "LMB Studio",
    "link_thumb": "https://live.staticflickr.com/65535/51787837899_28f7e3defd_o.gif",
    "link_bin": "https://github.com/lmbstudiocontact/mb5_3/raw/main/Boy_L6_537247328.bin",
    "id_bin": "Boy_L6_537247328",
    "list_language": [
      {
        "author": "LMB Studio",
        "link_thumb": "https://live.staticflickr.com/65535/51787215691_f153f39913_o.gif",
        "link_bin": "https://github.com/lmbstudiocontact/mb5_3/raw/main/Boy_L6_537247328_English.bin",
        "name_language": "English",
        "id_bin_language": "Boy_L6_537247328_English"
      },
      {
        "author": "LMB Studio",
        "link_thumb": "https://live.staticflickr.com/65535/51787465198_222838db65_o.gif",
        "link_bin": "https://github.com/lmbstudiocontact/mb5_3/raw/main/Boy_L6_537247328_Portuguese.bin",
        "name_language": "Portuguese",
        "id_bin_language": "Boy_L6_537247328_Portuguese"
      },
      {
        "author": "LMB Studio",
        "link_thumb": "https://live.staticflickr.com/65535/51787465128_474cf2e7a7_o.gif",
        "link_bin": "https://github.com/lmbstudiocontact/mb5_3/raw/main/Boy_L6_537247328_Russian.bin",
        "name_language": "Russian",
        "id_bin_language": "Boy_L6_537247328_Russian"
      },
      {
        "author": "LMB Studio",
        "link_thumb": "https://live.staticflickr.com/65535/51787837759_b3e1094b17_o.gif",
        "link_bin": "https://github.com/lmbstudiocontact/mb5_3/raw/main/Boy_L6_537247328_Spanish.bin",
        "name_language": "Spanish",
        "id_bin_language": "Boy_L6_537247328_Spanish"
      }
    ],
    "array_tags": [
      "lmbstudio"
    ],
    "list_album": [
      {
        "id_album": "1995733213",
        "link_thumb": "https://live.staticflickr.com/65535/51787837899_28f7e3defd_o.gif",
        "title": "Boy_L6"
      }
    ]
  },
  {
    "author": "LMB Studio",
    "link_thumb": "https://live.staticflickr.com/65535/51787215516_6978d64318_o.gif",
    "link_bin": "https://github.com/lmbstudiocontact/mb5_3/raw/main/Boy_L6_537247521.bin",
    "id_bin": "Boy_L6_537247521",
    "list_language": [
      {
        "author": "LMB Studio",
        "link_thumb": "https://live.staticflickr.com/65535/51787215471_d641097741_o.gif",
        "link_bin": "https://github.com/lmbstudiocontact/mb5_3/raw/main/Boy_L6_537247521_English.bin",
        "name_language": "English",
        "id_bin_language": "Boy_L6_537247521_English"
      },
      {
        "author": "LMB Studio",
        "link_thumb": "https://live.staticflickr.com/65535/51787215431_da7a375607_o.gif",
        "link_bin": "https://github.com/lmbstudiocontact/mb5_3/raw/main/Boy_L6_537247521_Portuguese.bin",
        "name_language": "Portuguese",
        "id_bin_language": "Boy_L6_537247521_Portuguese"
      },
      {
        "author": "LMB Studio",
        "link_thumb": "https://live.staticflickr.com/65535/51787464988_1f3f5c0742_o.gif",
        "link_bin": "https://github.com/lmbstudiocontact/mb5_3/raw/main/Boy_L6_537247521_Russian.bin",
        "name_language": "Russian",
        "id_bin_language": "Boy_L6_537247521_Russian"
      },
      {
        "author": "LMB Studio",
        "link_thumb": "https://live.staticflickr.com/65535/51786397087_ca56844622_o.gif",
        "link_bin": "https://github.com/lmbstudiocontact/mb5_3/raw/main/Boy_L6_537247521_Spanish.bin",
        "name_language": "Spanish",
        "id_bin_language": "Boy_L6_537247521_Spanish"
      }
    ],
    "array_tags": [
      "lmbstudio"
    ],
    "list_album": [
      {
        "id_album": "1995733213",
        "link_thumb": "https://live.staticflickr.com/65535/51787215516_6978d64318_o.gif",
        "title": "Boy_L6"
      }
    ]
  },
  {
    "author": "LMB Studio",
    "link_thumb": "https://live.staticflickr.com/65535/51787451643_8e684e691d_o.gif",
    "link_bin": "https://github.com/lmbstudiocontact/mb5_3/raw/main/BuddhistTerms_L2_-1229196440.bin",
    "id_bin": "BuddhistTerms_L2_-1229196440",
    "list_language": [
      {
        "author": "LMB Studio",
        "link_thumb": "https://live.staticflickr.com/65535/51787451603_056064da04_o.gif",
        "link_bin": "https://github.com/lmbstudiocontact/mb5_3/raw/main/BuddhistTerms_L2_-1229196440_English.bin",
        "name_language": "English",
        "id_bin_language": "BuddhistTerms_L2_-1229196440_English"
      },
      {
        "author": "LMB Studio",
        "link_thumb": "https://live.staticflickr.com/65535/51786384087_09bf1e2100_o.gif",
        "link_bin": "https://github.com/lmbstudiocontact/mb5_3/raw/main/BuddhistTerms_L2_-1229196440_Portuguese.bin",
        "name_language": "Portuguese",
        "id_bin_language": "BuddhistTerms_L2_-1229196440_Portuguese"
      },
      {
        "author": "LMB Studio",
        "link_thumb": "https://live.staticflickr.com/65535/51786384057_eb00d61e52_o.gif",
        "link_bin": "https://github.com/lmbstudiocontact/mb5_3/raw/main/BuddhistTerms_L2_-1229196440_Russian.bin",
        "name_language": "Russian",
        "id_bin_language": "BuddhistTerms_L2_-1229196440_Russian"
      },
      {
        "author": "LMB Studio",
        "link_thumb": "https://live.staticflickr.com/65535/51786384022_8e5ffb48c8_o.gif",
        "link_bin": "https://github.com/lmbstudiocontact/mb5_3/raw/main/BuddhistTerms_L2_-1229196440_Spanish.bin",
        "name_language": "Spanish",
        "id_bin_language": "BuddhistTerms_L2_-1229196440_Spanish"
      }
    ],
    "array_tags": [
      "lmbstudio"
    ],
    "list_album": [
      {
        "id_album": "518853929",
        "link_thumb": "https://live.staticflickr.com/65535/51787451643_8e684e691d_o.gif",
        "title": "Buddhist Terms_L2"
      }
    ]
  },
  {
    "author": "LMB Studio",
    "link_thumb": "https://live.staticflickr.com/65535/51787824004_d0ac6600a4_o.gif",
    "link_bin": "https://github.com/lmbstudiocontact/mb5_3/raw/main/BuddhistTerms_L2_-1732681415.bin",
    "id_bin": "BuddhistTerms_L2_-1732681415",
    "list_language": [
      {
        "author": "LMB Studio",
        "link_thumb": "https://live.staticflickr.com/65535/51788073620_7b9c61b9aa_o.gif",
        "link_bin": "https://github.com/lmbstudiocontact/mb5_3/raw/main/BuddhistTerms_L2_-1732681415_English.bin",
        "name_language": "English",
        "id_bin_language": "BuddhistTerms_L2_-1732681415_English"
      },
      {
        "author": "LMB Studio",
        "link_thumb": "https://live.staticflickr.com/65535/51787823954_a8bbb0f419_o.gif",
        "link_bin": "https://github.com/lmbstudiocontact/mb5_3/raw/main/BuddhistTerms_L2_-1732681415_Portuguese.bin",
        "name_language": "Portuguese",
        "id_bin_language": "BuddhistTerms_L2_-1732681415_Portuguese"
      },
      {
        "author": "LMB Studio",
        "link_thumb": "https://live.staticflickr.com/65535/51787201701_134ed63973_o.gif",
        "link_bin": "https://github.com/lmbstudiocontact/mb5_3/raw/main/BuddhistTerms_L2_-1732681415_Russian.bin",
        "name_language": "Russian",
        "id_bin_language": "BuddhistTerms_L2_-1732681415_Russian"
      },
      {
        "author": "LMB Studio",
        "link_thumb": "https://live.staticflickr.com/65535/51787823889_a556e406c3_o.gif",
        "link_bin": "https://github.com/lmbstudiocontact/mb5_3/raw/main/BuddhistTerms_L2_-1732681415_Spanish.bin",
        "name_language": "Spanish",
        "id_bin_language": "BuddhistTerms_L2_-1732681415_Spanish"
      }
    ],
    "array_tags": [
      "lmbstudio"
    ],
    "list_album": [
      {
        "id_album": "518853929",
        "link_thumb": "https://live.staticflickr.com/65535/51787824004_d0ac6600a4_o.gif",
        "title": "Buddhist Terms_L2"
      }
    ]
  },
  {
    "author": "LMB Studio",
    "link_thumb": "https://live.staticflickr.com/65535/51787823869_94386f4748_o.gif",
    "link_bin": "https://github.com/lmbstudiocontact/mb5_3/raw/main/BuddhistTerms_L2_-1878387206.bin",
    "id_bin": "BuddhistTerms_L2_-1878387206",
    "list_language": [
      {
        "author": "LMB Studio",
        "link_thumb": "https://live.staticflickr.com/65535/51786383472_cb7fd3a796_o.gif",
        "link_bin": "https://github.com/lmbstudiocontact/mb5_3/raw/main/BuddhistTerms_L2_-1878387206_English.bin",
        "name_language": "English",
        "id_bin_language": "BuddhistTerms_L2_-1878387206_English"
      },
      {
        "author": "LMB Studio",
        "link_thumb": "https://live.staticflickr.com/65535/51788073410_bb3006f42d_o.gif",
        "link_bin": "https://github.com/lmbstudiocontact/mb5_3/raw/main/BuddhistTerms_L2_-1878387206_Portuguese.bin",
        "name_language": "Portuguese",
        "id_bin_language": "BuddhistTerms_L2_-1878387206_Portuguese"
      },
      {
        "author": "LMB Studio",
        "link_thumb": "https://live.staticflickr.com/65535/51788073380_52695f5fa2_o.gif",
        "link_bin": "https://github.com/lmbstudiocontact/mb5_3/raw/main/BuddhistTerms_L2_-1878387206_Russian.bin",
        "name_language": "Russian",
        "id_bin_language": "BuddhistTerms_L2_-1878387206_Russian"
      },
      {
        "author": "LMB Studio",
        "link_thumb": "https://live.staticflickr.com/65535/51788073290_f2b56c755f_o.gif",
        "link_bin": "https://github.com/lmbstudiocontact/mb5_3/raw/main/BuddhistTerms_L2_-1878387206_Spanish.bin",
        "name_language": "Spanish",
        "id_bin_language": "BuddhistTerms_L2_-1878387206_Spanish"
      }
    ],
    "array_tags": [
      "lmbstudio"
    ],
    "list_album": [
      {
        "id_album": "518853929",
        "link_thumb": "https://live.staticflickr.com/65535/51787823869_94386f4748_o.gif",
        "title": "Buddhist Terms_L2"
      }
    ]
  },
  {
    "author": "LMB Studio",
    "link_thumb": "https://live.staticflickr.com/65535/51787450883_3bb12c3927_o.gif",
    "link_bin": "https://github.com/lmbstudiocontact/mb5_3/raw/main/BuddhistTerms_L2_-1889211601.bin",
    "id_bin": "BuddhistTerms_L2_-1889211601",
    "list_language": [
      {
        "author": "LMB Studio",
        "link_thumb": "https://live.staticflickr.com/65535/51787450868_f963fdac17_o.gif",
        "link_bin": "https://github.com/lmbstudiocontact/mb5_3/raw/main/BuddhistTerms_L2_-1889211601_English.bin",
        "name_language": "English",
        "id_bin_language": "BuddhistTerms_L2_-1889211601_English"
      },
      {
        "author": "LMB Studio",
        "link_thumb": "https://live.staticflickr.com/65535/51787201346_3a422e5327_o.gif",
        "link_bin": "https://github.com/lmbstudiocontact/mb5_3/raw/main/BuddhistTerms_L2_-1889211601_Portuguese.bin",
        "name_language": "Portuguese",
        "id_bin_language": "BuddhistTerms_L2_-1889211601_Portuguese"
      },
      {
        "author": "LMB Studio",
        "link_thumb": "https://live.staticflickr.com/65535/51788073100_0fcfc3dfaa_o.gif",
        "link_bin": "https://github.com/lmbstudiocontact/mb5_3/raw/main/BuddhistTerms_L2_-1889211601_Russian.bin",
        "name_language": "Russian",
        "id_bin_language": "BuddhistTerms_L2_-1889211601_Russian"
      },
      {
        "author": "LMB Studio",
        "link_thumb": "https://live.staticflickr.com/65535/51786383072_36a362cdb4_o.gif",
        "link_bin": "https://github.com/lmbstudiocontact/mb5_3/raw/main/BuddhistTerms_L2_-1889211601_Spanish.bin",
        "name_language": "Spanish",
        "id_bin_language": "BuddhistTerms_L2_-1889211601_Spanish"
      }
    ],
    "array_tags": [
      "lmbstudio"
    ],
    "list_album": [
      {
        "id_album": "518853929",
        "link_thumb": "https://live.staticflickr.com/65535/51787450883_3bb12c3927_o.gif",
        "title": "Buddhist Terms_L2"
      }
    ]
  },
  {
    "author": "LMB Studio",
    "link_thumb": "https://live.staticflickr.com/65535/51788072790_3dd35f767d_o.gif",
    "link_bin": "https://github.com/lmbstudiocontact/mb5_3/raw/main/BuddhistTerms_L2_-2076324624.bin",
    "id_bin": "BuddhistTerms_L2_-2076324624",
    "list_language": [
      {
        "author": "LMB Studio",
        "link_thumb": "https://live.staticflickr.com/65535/51787450323_21dc861621_o.gif",
        "link_bin": "https://github.com/lmbstudiocontact/mb5_3/raw/main/BuddhistTerms_L2_-2076324624_English.bin",
        "name_language": "English",
        "id_bin_language": "BuddhistTerms_L2_-2076324624_English"
      },
      {
        "author": "LMB Studio",
        "link_thumb": "https://live.staticflickr.com/65535/51786382692_2d3a243377_o.gif",
        "link_bin": "https://github.com/lmbstudiocontact/mb5_3/raw/main/BuddhistTerms_L2_-2076324624_Portuguese.bin",
        "name_language": "Portuguese",
        "id_bin_language": "BuddhistTerms_L2_-2076324624_Portuguese"
      },
      {
        "author": "LMB Studio",
        "link_thumb": "https://live.staticflickr.com/65535/51788072600_5867cc42fc_o.gif",
        "link_bin": "https://github.com/lmbstudiocontact/mb5_3/raw/main/BuddhistTerms_L2_-2076324624_Russian.bin",
        "name_language": "Russian",
        "id_bin_language": "BuddhistTerms_L2_-2076324624_Russian"
      },
      {
        "author": "LMB Studio",
        "link_thumb": "https://live.staticflickr.com/65535/51787450093_51d38eb785_o.gif",
        "link_bin": "https://github.com/lmbstudiocontact/mb5_3/raw/main/BuddhistTerms_L2_-2076324624_Spanish.bin",
        "name_language": "Spanish",
        "id_bin_language": "BuddhistTerms_L2_-2076324624_Spanish"
      }
    ],
    "array_tags": [
      "lmbstudio"
    ],
    "list_album": [
      {
        "id_album": "518853929",
        "link_thumb": "https://live.staticflickr.com/65535/51788072790_3dd35f767d_o.gif",
        "title": "Buddhist Terms_L2"
      }
    ]
  },
  {
    "author": "LMB Studio",
    "link_thumb": "https://live.staticflickr.com/65535/51787825629_71dc688def_o.gif",
    "link_bin": "https://github.com/lmbstudiocontact/mb5_3/raw/main/BuddhistTerms_L2_-210203802.bin",
    "id_bin": "BuddhistTerms_L2_-210203802",
    "list_language": [
      {
        "author": "LMB Studio",
        "link_thumb": "https://live.staticflickr.com/65535/51788075080_ea85c5faf6_o.gif",
        "link_bin": "https://github.com/lmbstudiocontact/mb5_3/raw/main/BuddhistTerms_L2_-210203802_English.bin",
        "name_language": "English",
        "id_bin_language": "BuddhistTerms_L2_-210203802_English"
      },
      {
        "author": "LMB Studio",
        "link_thumb": "https://live.staticflickr.com/65535/51788075040_102bbda871_o.gif",
        "link_bin": "https://github.com/lmbstudiocontact/mb5_3/raw/main/BuddhistTerms_L2_-210203802_Portuguese.bin",
        "name_language": "Portuguese",
        "id_bin_language": "BuddhistTerms_L2_-210203802_Portuguese"
      },
      {
        "author": "LMB Studio",
        "link_thumb": "https://live.staticflickr.com/65535/51788074990_d47212a9f7_o.gif",
        "link_bin": "https://github.com/lmbstudiocontact/mb5_3/raw/main/BuddhistTerms_L2_-210203802_Russian.bin",
        "name_language": "Russian",
        "id_bin_language": "BuddhistTerms_L2_-210203802_Russian"
      },
      {
        "author": "LMB Studio",
        "link_thumb": "https://live.staticflickr.com/65535/51788074975_fa067f6539_o.gif",
        "link_bin": "https://github.com/lmbstudiocontact/mb5_3/raw/main/BuddhistTerms_L2_-210203802_Spanish.bin",
        "name_language": "Spanish",
        "id_bin_language": "BuddhistTerms_L2_-210203802_Spanish"
      }
    ],
    "array_tags": [
      "lmbstudio"
    ],
    "list_album": [
      {
        "id_album": "518853929",
        "link_thumb": "https://live.staticflickr.com/65535/51787825629_71dc688def_o.gif",
        "title": "Buddhist Terms_L2"
      }
    ]
  },
  {
    "author": "LMB Studio",
    "link_thumb": "https://live.staticflickr.com/65535/51787825494_245d0fae70_o.gif",
    "link_bin": "https://github.com/lmbstudiocontact/mb5_3/raw/main/BuddhistTerms_L2_-416000018.bin",
    "id_bin": "BuddhistTerms_L2_-416000018",
    "list_language": [
      {
        "author": "LMB Studio",
        "link_thumb": "https://live.staticflickr.com/65535/51787452518_2dc413932a_o.gif",
        "link_bin": "https://github.com/lmbstudiocontact/mb5_27/raw/main/BuddhistTerms_L2_-416000018_English.bin",
        "name_language": "English",
        "id_bin_language": "BuddhistTerms_L2_-416000018_English"
      },
      {
        "author": "LMB Studio",
        "link_thumb": "https://live.staticflickr.com/65535/51786385177_828f0efbbf_o.gif",
        "link_bin": "https://github.com/lmbstudiocontact/mb5_27/raw/main/BuddhistTerms_L2_-416000018_Portuguese.bin",
        "name_language": "Portuguese",
        "id_bin_language": "BuddhistTerms_L2_-416000018_Portuguese"
      },
      {
        "author": "LMB Studio",
        "link_thumb": "https://live.staticflickr.com/65535/51787825379_4cb8a499a1_o.gif",
        "link_bin": "https://github.com/lmbstudiocontact/mb5_27/raw/main/BuddhistTerms_L2_-416000018_Russian.bin",
        "name_language": "Russian",
        "id_bin_language": "BuddhistTerms_L2_-416000018_Russian"
      },
      {
        "author": "LMB Studio",
        "link_thumb": "https://live.staticflickr.com/65535/51787825344_71b140e3cd_o.gif",
        "link_bin": "https://github.com/lmbstudiocontact/mb5_27/raw/main/BuddhistTerms_L2_-416000018_Spanish.bin",
        "name_language": "Spanish",
        "id_bin_language": "BuddhistTerms_L2_-416000018_Spanish"
      }
    ],
    "array_tags": [
      "lmbstudio"
    ],
    "list_album": [
      {
        "id_album": "518853929",
        "link_thumb": "https://live.staticflickr.com/65535/51787825494_245d0fae70_o.gif",
        "title": "Buddhist Terms_L2"
      }
    ]
  },
  {
    "author": "LMB Studio",
    "link_thumb": "https://live.staticflickr.com/65535/51787839199_0e1b9d328b_o.gif",
    "link_bin": "https://github.com/lmbstudiocontact/mb5_30/raw/main/DragonArt_L5_-145384018.bin",
    "id_bin": "DragonArt_L5_-145384018",
    "list_language": [
      {
        "author": "LMB Studio",
        "link_thumb": "https://live.staticflickr.com/65535/51787216936_d3c17f4cbb_o.gif",
        "link_bin": "https://github.com/lmbstudiocontact/mb5_30/raw/main/DragonArt_L5_-145384018_English.bin",
        "name_language": "English",
        "id_bin_language": "DragonArt_L5_-145384018_English"
      },
      {
        "author": "LMB Studio",
        "link_thumb": "https://live.staticflickr.com/65535/51787216906_d85c171f87_o.gif",
        "link_bin": "https://github.com/lmbstudiocontact/mb5_30/raw/main/DragonArt_L5_-145384018_Portuguese.bin",
        "name_language": "Portuguese",
        "id_bin_language": "DragonArt_L5_-145384018_Portuguese"
      },
      {
        "author": "LMB Studio",
        "link_thumb": "https://live.staticflickr.com/65535/51786398482_3ffbc4918b_o.gif",
        "link_bin": "https://github.com/lmbstudiocontact/mb5_30/raw/main/DragonArt_L5_-145384018_Russian.bin",
        "name_language": "Russian",
        "id_bin_language": "DragonArt_L5_-145384018_Russian"
      },
      {
        "author": "LMB Studio",
        "link_thumb": "https://live.staticflickr.com/65535/51788088505_d0cf5d3c65_o.gif",
        "link_bin": "https://github.com/lmbstudiocontact/mb5_30/raw/main/DragonArt_L5_-145384018_Spanish.bin",
        "name_language": "Spanish",
        "id_bin_language": "DragonArt_L5_-145384018_Spanish"
      }
    ],
    "array_tags": [
      "lmbstudio"
    ],
    "list_album": [
      {
        "id_album": "2059014002",
        "link_thumb": "https://live.staticflickr.com/65535/51787839199_0e1b9d328b_o.gif",
        "title": "Dragon Art_L5"
      }
    ]
  },
  {
    "author": "LMB Studio",
    "link_thumb": "https://live.staticflickr.com/65535/51786398422_57dc148df6_o.gif",
    "link_bin": "https://github.com/lmbstudiocontact/mb5_30/raw/main/DragonArt_L5_-145415856.bin",
    "id_bin": "DragonArt_L5_-145415856",
    "list_language": [
      {
        "author": "LMB Studio",
        "link_thumb": "https://live.staticflickr.com/65535/51787216796_0525ea549a_o.gif",
        "link_bin": "https://github.com/lmbstudiocontact/mb5_30/raw/main/DragonArt_L5_-145415856_English.bin",
        "name_language": "English",
        "id_bin_language": "DragonArt_L5_-145415856_English"
      },
      {
        "author": "LMB Studio",
        "link_thumb": "https://live.staticflickr.com/65535/51786398347_9e28fd40e6_o.gif",
        "link_bin": "https://github.com/lmbstudiocontact/mb5_30/raw/main/DragonArt_L5_-145415856_Portuguese.bin",
        "name_language": "Portuguese",
        "id_bin_language": "DragonArt_L5_-145415856_Portuguese"
      },
      {
        "author": "LMB Studio",
        "link_thumb": "https://live.staticflickr.com/65535/51788088325_363f2327a7_o.gif",
        "link_bin": "https://github.com/lmbstudiocontact/mb5_30/raw/main/DragonArt_L5_-145415856_Russian.bin",
        "name_language": "Russian",
        "id_bin_language": "DragonArt_L5_-145415856_Russian"
      },
      {
        "author": "LMB Studio",
        "link_thumb": "https://live.staticflickr.com/65535/51787216701_e424ac293e_o.gif",
        "link_bin": "https://github.com/lmbstudiocontact/mb5_30/raw/main/DragonArt_L5_-145415856_Spanish.bin",
        "name_language": "Spanish",
        "id_bin_language": "DragonArt_L5_-145415856_Spanish"
      }
    ],
    "array_tags": [
      "lmbstudio"
    ],
    "list_album": [
      {
        "id_album": "2059014002",
        "link_thumb": "https://live.staticflickr.com/65535/51786398422_57dc148df6_o.gif",
        "title": "Dragon Art_L5"
      }
    ]
  },
  {
    "author": "LMB Studio",
    "link_thumb": "https://live.staticflickr.com/65535/51787216656_392b04cf88_o.gif",
    "link_bin": "https://github.com/lmbstudiocontact/mb5_30/raw/main/DragonArt_L5_-145415857.bin",
    "id_bin": "DragonArt_L5_-145415857",
    "list_language": [
      {
        "author": "LMB Studio",
        "link_thumb": "https://live.staticflickr.com/65535/51787466023_a2f91981cd_o.gif",
        "link_bin": "https://github.com/lmbstudiocontact/mb5_30/raw/main/DragonArt_L5_-145415857_English.bin",
        "name_language": "English",
        "id_bin_language": "DragonArt_L5_-145415857_English"
      },
      {
        "author": "LMB Studio",
        "link_thumb": "https://live.staticflickr.com/65535/51787216566_24042cf800_o.gif",
        "link_bin": "https://github.com/lmbstudiocontact/mb5_30/raw/main/DragonArt_L5_-145415857_Portuguese.bin",
        "name_language": "Portuguese",
        "id_bin_language": "DragonArt_L5_-145415857_Portuguese"
      },
      {
        "author": "LMB Studio",
        "link_thumb": "https://live.staticflickr.com/65535/51786398192_29e2846887_o.gif",
        "link_bin": "https://github.com/lmbstudiocontact/mb5_30/raw/main/DragonArt_L5_-145415857_Russian.bin",
        "name_language": "Russian",
        "id_bin_language": "DragonArt_L5_-145415857_Russian"
      },
      {
        "author": "LMB Studio",
        "link_thumb": "https://live.staticflickr.com/65535/51788088085_1c729266f2_o.gif",
        "link_bin": "https://github.com/lmbstudiocontact/mb5_30/raw/main/DragonArt_L5_-145415857_Spanish.bin",
        "name_language": "Spanish",
        "id_bin_language": "DragonArt_L5_-145415857_Spanish"
      }
    ],
    "array_tags": [
      "lmbstudio"
    ],
    "list_album": [
      {
        "id_album": "2059014002",
        "link_thumb": "https://live.staticflickr.com/65535/51787216656_392b04cf88_o.gif",
        "title": "Dragon Art_L5"
      }
    ]
  },
  {
    "author": "LMB Studio",
    "link_thumb": "https://live.staticflickr.com/65535/51788088010_edecc023e0_o.gif",
    "link_bin": "https://github.com/lmbstudiocontact/mb5_30/raw/main/DragonArt_L5_-145415858.bin",
    "id_bin": "DragonArt_L5_-145415858",
    "list_language": [
      {
        "author": "LMB Studio",
        "link_thumb": "https://live.staticflickr.com/65535/51788087970_8357620ab5_o.gif",
        "link_bin": "https://github.com/lmbstudiocontact/mb5_30/raw/main/DragonArt_L5_-145415858_English.bin",
        "name_language": "English",
        "id_bin_language": "DragonArt_L5_-145415858_English"
      },
      {
        "author": "LMB Studio",
        "link_thumb": "https://live.staticflickr.com/65535/51786398022_f526a861fc_o.gif",
        "link_bin": "https://github.com/lmbstudiocontact/mb5_30/raw/main/DragonArt_L5_-145415858_Portuguese.bin",
        "name_language": "Portuguese",
        "id_bin_language": "DragonArt_L5_-145415858_Portuguese"
      },
      {
        "author": "LMB Studio",
        "link_thumb": "https://live.staticflickr.com/65535/51786397992_b7dfd16e78_o.gif",
        "link_bin": "https://github.com/lmbstudiocontact/mb5_30/raw/main/DragonArt_L5_-145415858_Russian.bin",
        "name_language": "Russian",
        "id_bin_language": "DragonArt_L5_-145415858_Russian"
      },
      {
        "author": "LMB Studio",
        "link_thumb": "https://live.staticflickr.com/65535/51787838389_e2ce067b10_o.gif",
        "link_bin": "https://github.com/lmbstudiocontact/mb5_30/raw/main/DragonArt_L5_-145415858_Spanish.bin",
        "name_language": "Spanish",
        "id_bin_language": "DragonArt_L5_-145415858_Spanish"
      }
    ],
    "array_tags": [
      "lmbstudio"
    ],
    "list_album": [
      {
        "id_album": "2059014002",
        "link_thumb": "https://live.staticflickr.com/65535/51788088010_edecc023e0_o.gif",
        "title": "Dragon Art_L5"
      }
    ]
  },
  {
    "author": "LMB Studio",
    "link_thumb": "https://live.staticflickr.com/65535/51786396812_2ed5eb3322_o.gif",
    "link_bin": "https://github.com/lmbstudiocontact/mb5_30/raw/main/DragonArt_L5_-1479946117.bin",
    "id_bin": "DragonArt_L5_-1479946117",
    "list_language": [
      {
        "author": "LMB Studio",
        "link_thumb": "https://live.staticflickr.com/65535/51786396767_290d0ef90b_o.gif",
        "link_bin": "https://github.com/lmbstudiocontact/mb5_30/raw/main/DragonArt_L5_-1479946117_English.bin",
        "name_language": "English",
        "id_bin_language": "DragonArt_L5_-1479946117_English"
      },
      {
        "author": "LMB Studio",
        "link_thumb": "https://live.staticflickr.com/65535/51788086695_9a2d7abc1c_o.gif",
        "link_bin": "https://github.com/lmbstudiocontact/mb5_30/raw/main/DragonArt_L5_-1479946117_Portuguese.bin",
        "name_language": "Portuguese",
        "id_bin_language": "DragonArt_L5_-1479946117_Portuguese"
      },
      {
        "author": "LMB Studio",
        "link_thumb": "https://live.staticflickr.com/65535/51787837219_12edfc7b8d_o.gif",
        "link_bin": "https://github.com/lmbstudiocontact/mb5_30/raw/main/DragonArt_L5_-1479946117_Russian.bin",
        "name_language": "Russian",
        "id_bin_language": "DragonArt_L5_-1479946117_Russian"
      },
      {
        "author": "LMB Studio",
        "link_thumb": "https://live.staticflickr.com/65535/51787214896_139743e097_o.gif",
        "link_bin": "https://github.com/lmbstudiocontact/mb5_30/raw/main/DragonArt_L5_-1479946117_Spanish.bin",
        "name_language": "Spanish",
        "id_bin_language": "DragonArt_L5_-1479946117_Spanish"
      }
    ],
    "array_tags": [
      "lmbstudio"
    ],
    "list_album": [
      {
        "id_album": "2059014002",
        "link_thumb": "https://live.staticflickr.com/65535/51786396812_2ed5eb3322_o.gif",
        "title": "Dragon Art_L5"
      }
    ]
  },
  {
    "author": "LMB Studio",
    "link_thumb": "https://live.staticflickr.com/65535/51787215601_c8c0baa9bd_o.gif",
    "link_bin": "https://github.com/lmbstudiocontact/mb5_30/raw/main/DragonArt_L5_-382965120.bin",
    "id_bin": "DragonArt_L5_-382965120",
    "list_language": [
      {
        "author": "LMB Studio",
        "link_thumb": "https://live.staticflickr.com/65535/51787215571_10b0db0188_o.gif",
        "link_bin": "https://github.com/lmbstudiocontact/mb5_30/raw/main/DragonArt_L5_-382965120_English.bin",
        "name_language": "English",
        "id_bin_language": "DragonArt_L5_-382965120_English"
      },
      {
        "author": "LMB Studio",
        "link_thumb": "https://live.staticflickr.com/65535/51786397247_0c224b25aa_o.gif",
        "link_bin": "https://github.com/lmbstudiocontact/mb5_30/raw/main/DragonArt_L5_-382965120_Portuguese.bin",
        "name_language": "Portuguese",
        "id_bin_language": "DragonArt_L5_-382965120_Portuguese"
      },
      {
        "author": "LMB Studio",
        "link_thumb": "https://live.staticflickr.com/65535/51787465033_dbb0b6445b_o.gif",
        "link_bin": "https://github.com/lmbstudiocontact/mb5_30/raw/main/DragonArt_L5_-382965120_Russian.bin",
        "name_language": "Russian",
        "id_bin_language": "DragonArt_L5_-382965120_Russian"
      },
      {
        "author": "LMB Studio",
        "link_thumb": "https://live.staticflickr.com/65535/51787465013_f7280d6dba_o.gif",
        "link_bin": "https://github.com/lmbstudiocontact/mb5_30/raw/main/DragonArt_L5_-382965120_Spanish.bin",
        "name_language": "Spanish",
        "id_bin_language": "DragonArt_L5_-382965120_Spanish"
      }
    ],
    "array_tags": [
      "lmbstudio"
    ],
    "list_album": [
      {
        "id_album": "2059014002",
        "link_thumb": "https://live.staticflickr.com/65535/51787215601_c8c0baa9bd_o.gif",
        "title": "Dragon Art_L5"
      }
    ]
  },
  {
    "author": "LMB Studio",
    "link_thumb": "https://live.staticflickr.com/65535/51788087065_c7f5ee6b32_o.gif",
    "link_bin": "https://github.com/lmbstudiocontact/mb5_30/raw/main/DragonArt_L5_-382965121.bin",
    "id_bin": "DragonArt_L5_-382965121",
    "list_language": [
      {
        "author": "LMB Studio",
        "link_thumb": "https://live.staticflickr.com/65535/51786397092_ea6c5ff09a_o.gif",
        "link_bin": "https://github.com/lmbstudiocontact/mb5_30/raw/main/DragonArt_L5_-382965121_English.bin",
        "name_language": "English",
        "id_bin_language": "DragonArt_L5_-382965121_English"
      },
      {
        "author": "LMB Studio",
        "link_thumb": "https://live.staticflickr.com/65535/51786397072_19a9bd0088_o.gif",
        "link_bin": "https://github.com/lmbstudiocontact/mb5_30/raw/main/DragonArt_L5_-382965121_Portuguese.bin",
        "name_language": "Portuguese",
        "id_bin_language": "DragonArt_L5_-382965121_Portuguese"
      },
      {
        "author": "LMB Studio",
        "link_thumb": "https://live.staticflickr.com/65535/51787215296_4d8ef63920_o.gif",
        "link_bin": "https://github.com/lmbstudiocontact/mb5_30/raw/main/DragonArt_L5_-382965121_Russian.bin",
        "name_language": "Russian",
        "id_bin_language": "DragonArt_L5_-382965121_Russian"
      },
      {
        "author": "LMB Studio",
        "link_thumb": "https://live.staticflickr.com/65535/51786397022_a4decdc214_o.gif",
        "link_bin": "https://github.com/lmbstudiocontact/mb5_30/raw/main/DragonArt_L5_-382965121_Spanish.bin",
        "name_language": "Spanish",
        "id_bin_language": "DragonArt_L5_-382965121_Spanish"
      }
    ],
    "array_tags": [
      "lmbstudio"
    ],
    "list_album": [
      {
        "id_album": "2059014002",
        "link_thumb": "https://live.staticflickr.com/65535/51788087065_c7f5ee6b32_o.gif",
        "title": "Dragon Art_L5"
      }
    ]
  },
  {
    "author": "LMB Studio",
    "link_thumb": "https://live.staticflickr.com/65535/51786396982_a6912ac9e6_o.gif",
    "link_bin": "https://github.com/lmbstudiocontact/mb5_30/raw/main/DragonArt_L5_-382993955.bin",
    "id_bin": "DragonArt_L5_-382993955",
    "list_language": [
      {
        "author": "LMB Studio",
        "link_thumb": "https://live.staticflickr.com/65535/51787215131_c1e7f3a809_o.gif",
        "link_bin": "https://github.com/lmbstudiocontact/mb5_30/raw/main/DragonArt_L5_-382993955_English.bin",
        "name_language": "English",
        "id_bin_language": "DragonArt_L5_-382993955_English"
      },
      {
        "author": "LMB Studio",
        "link_thumb": "https://live.staticflickr.com/65535/51787464803_67d27799e2_o.gif",
        "link_bin": "https://github.com/lmbstudiocontact/mb5_30/raw/main/DragonArt_L5_-382993955_Portuguese.bin",
        "name_language": "Portuguese",
        "id_bin_language": "DragonArt_L5_-382993955_Portuguese"
      },
      {
        "author": "LMB Studio",
        "link_thumb": "https://live.staticflickr.com/65535/51787215056_5a7cbf06cb_o.gif",
        "link_bin": "https://github.com/lmbstudiocontact/mb5_30/raw/main/DragonArt_L5_-382993955_Russian.bin",
        "name_language": "Russian",
        "id_bin_language": "DragonArt_L5_-382993955_Russian"
      },
      {
        "author": "LMB Studio",
        "link_thumb": "https://live.staticflickr.com/65535/51787214996_d9681b7b7a_o.gif",
        "link_bin": "https://github.com/lmbstudiocontact/mb5_30/raw/main/DragonArt_L5_-382993955_Spanish.bin",
        "name_language": "Spanish",
        "id_bin_language": "DragonArt_L5_-382993955_Spanish"
      }
    ],
    "array_tags": [
      "lmbstudio"
    ],
    "list_album": [
      {
        "id_album": "2059014002",
        "link_thumb": "https://live.staticflickr.com/65535/51786396982_a6912ac9e6_o.gif",
        "title": "Dragon Art_L5"
      }
    ]
  },
  {
    "author": "LMB Studio",
    "link_thumb": "https://live.staticflickr.com/65535/51787464478_e9231fd832_o.gif",
    "link_bin": "https://github.com/lmbstudiocontact/mb5_30/raw/main/DragonArt_L5_1764991579.bin",
    "id_bin": "DragonArt_L5_1764991579",
    "list_language": [
      {
        "author": "LMB Studio",
        "link_thumb": "https://live.staticflickr.com/65535/51787837104_cea0a81d05_o.gif",
        "link_bin": "https://github.com/lmbstudiocontact/mb5_30/raw/main/DragonArt_L5_1764991579_English.bin",
        "name_language": "English",
        "id_bin_language": "DragonArt_L5_1764991579_English"
      },
      {
        "author": "LMB Studio",
        "link_thumb": "https://live.staticflickr.com/65535/51787464403_fc8efe24f0_o.gif",
        "link_bin": "https://github.com/lmbstudiocontact/mb5_30/raw/main/DragonArt_L5_1764991579_Portuguese.bin",
        "name_language": "Portuguese",
        "id_bin_language": "DragonArt_L5_1764991579_Portuguese"
      },
      {
        "author": "LMB Studio",
        "link_thumb": "https://live.staticflickr.com/65535/51786396502_33dd51a133_o.gif",
        "link_bin": "https://github.com/lmbstudiocontact/mb5_30/raw/main/DragonArt_L5_1764991579_Russian.bin",
        "name_language": "Russian",
        "id_bin_language": "DragonArt_L5_1764991579_Russian"
      },
      {
        "author": "LMB Studio",
        "link_thumb": "https://live.staticflickr.com/65535/51786396447_e1dd417dd3_o.gif",
        "link_bin": "https://github.com/lmbstudiocontact/mb5_30/raw/main/DragonArt_L5_1764991579_Spanish.bin",
        "name_language": "Spanish",
        "id_bin_language": "DragonArt_L5_1764991579_Spanish"
      }
    ],
    "array_tags": [
      "lmbstudio"
    ],
    "list_album": [
      {
        "id_album": "2059014002",
        "link_thumb": "https://live.staticflickr.com/65535/51787464478_e9231fd832_o.gif",
        "title": "Dragon Art_L5"
      }
    ]
  },
  {
    "author": "LMB Studio",
    "link_thumb": "https://live.staticflickr.com/65535/51787214596_781ce5106d_o.gif",
    "link_bin": "https://github.com/lmbstudiocontact/mb5_30/raw/main/DragonArt_L5_1895808341.bin",
    "id_bin": "DragonArt_L5_1895808341",
    "list_language": [
      {
        "author": "LMB Studio",
        "link_thumb": "https://live.staticflickr.com/65535/51786396392_59c2f7ecd9_o.gif",
        "link_bin": "https://github.com/lmbstudiocontact/mb5_30/raw/main/DragonArt_L5_1895808341_English.bin",
        "name_language": "English",
        "id_bin_language": "DragonArt_L5_1895808341_English"
      },
      {
        "author": "LMB Studio",
        "link_thumb": "https://live.staticflickr.com/65535/51787464168_da0ed8666a_o.gif",
        "link_bin": "https://github.com/lmbstudiocontact/mb5_30/raw/main/DragonArt_L5_1895808341_Portuguese.bin",
        "name_language": "Portuguese",
        "id_bin_language": "DragonArt_L5_1895808341_Portuguese"
      },
      {
        "author": "LMB Studio",
        "link_thumb": "https://live.staticflickr.com/65535/51787464143_545b403462_o.gif",
        "link_bin": "https://github.com/lmbstudiocontact/mb5_30/raw/main/DragonArt_L5_1895808341_Russian.bin",
        "name_language": "Russian",
        "id_bin_language": "DragonArt_L5_1895808341_Russian"
      },
      {
        "author": "LMB Studio",
        "link_thumb": "https://live.staticflickr.com/65535/51786396327_93f2775726_o.gif",
        "link_bin": "https://github.com/lmbstudiocontact/mb5_30/raw/main/DragonArt_L5_1895808341_Spanish.bin",
        "name_language": "Spanish",
        "id_bin_language": "DragonArt_L5_1895808341_Spanish"
      }
    ],
    "array_tags": [
      "lmbstudio"
    ],
    "list_album": [
      {
        "id_album": "2059014002",
        "link_thumb": "https://live.staticflickr.com/65535/51787214596_781ce5106d_o.gif",
        "title": "Dragon Art_L5"
      }
    ]
  },
  {
    "author": "LMB Studio",
    "link_thumb": "https://live.staticflickr.com/65535/51786397867_e0f29559cd_o.gif",
    "link_bin": "https://github.com/lmbstudiocontact/mb5_30/raw/main/DragonArt_L5_366228268.bin",
    "id_bin": "DragonArt_L5_366228268",
    "list_language": [
      {
        "author": "LMB Studio",
        "link_thumb": "https://live.staticflickr.com/65535/51788087750_f1c3bfee13_o.gif",
        "link_bin": "https://github.com/lmbstudiocontact/mb5_30/raw/main/DragonArt_L5_366228268_English.bin",
        "name_language": "English",
        "id_bin_language": "DragonArt_L5_366228268_English"
      },
      {
        "author": "LMB Studio",
        "link_thumb": "https://live.staticflickr.com/65535/51788087685_dbb03a5e4d_o.gif",
        "link_bin": "https://github.com/lmbstudiocontact/mb5_30/raw/main/DragonArt_L5_366228268_Portuguese.bin",
        "name_language": "Portuguese",
        "id_bin_language": "DragonArt_L5_366228268_Portuguese"
      },
      {
        "author": "LMB Studio",
        "link_thumb": "https://live.staticflickr.com/65535/51787216041_54fddedb01_o.gif",
        "link_bin": "https://github.com/lmbstudiocontact/mb5_30/raw/main/DragonArt_L5_366228268_Russian.bin",
        "name_language": "Russian",
        "id_bin_language": "DragonArt_L5_366228268_Russian"
      },
      {
        "author": "LMB Studio",
        "link_thumb": "https://live.staticflickr.com/65535/51787838104_82b263b7a0_o.gif",
        "link_bin": "https://github.com/lmbstudiocontact/mb5_30/raw/main/DragonArt_L5_366228268_Spanish.bin",
        "name_language": "Spanish",
        "id_bin_language": "DragonArt_L5_366228268_Spanish"
      }
    ],
    "array_tags": [
      "lmbstudio"
    ],
    "list_album": [
      {
        "id_album": "2059014002",
        "link_thumb": "https://live.staticflickr.com/65535/51786397867_e0f29559cd_o.gif",
        "title": "Dragon Art_L5"
      }
    ]
  },
  {
    "author": "LMB Studio",
    "link_thumb": "https://live.staticflickr.com/65535/51787465483_4162c47bf0_o.gif",
    "link_bin": "https://github.com/lmbstudiocontact/mb5_30/raw/main/DragonArt_L5_366228269.bin",
    "id_bin": "DragonArt_L5_366228269",
    "list_language": [
      {
        "author": "LMB Studio",
        "link_thumb": "https://live.staticflickr.com/65535/51786397582_52d88b92fc_o.gif",
        "link_bin": "https://github.com/lmbstudiocontact/mb5_30/raw/main/DragonArt_L5_366228269_English.bin",
        "name_language": "English",
        "id_bin_language": "DragonArt_L5_366228269_English"
      },
      {
        "author": "LMB Studio",
        "link_thumb": "https://live.staticflickr.com/65535/51788087485_7da50961e6_o.gif",
        "link_bin": "https://github.com/lmbstudiocontact/mb5_30/raw/main/DragonArt_L5_366228269_Portuguese.bin",
        "name_language": "Portuguese",
        "id_bin_language": "DragonArt_L5_366228269_Portuguese"
      },
      {
        "author": "LMB Studio",
        "link_thumb": "https://live.staticflickr.com/65535/51787838029_9ff5253be9_o.gif",
        "link_bin": "https://github.com/lmbstudiocontact/mb5_30/raw/main/DragonArt_L5_366228269_Russian.bin",
        "name_language": "Russian",
        "id_bin_language": "DragonArt_L5_366228269_Russian"
      },
      {
        "author": "LMB Studio",
        "link_thumb": "https://live.staticflickr.com/65535/51787465353_9d7bd47877_o.gif",
        "link_bin": "https://github.com/lmbstudiocontact/mb5_30/raw/main/DragonArt_L5_366228269_Spanish.bin",
        "name_language": "Spanish",
        "id_bin_language": "DragonArt_L5_366228269_Spanish"
      }
    ],
    "array_tags": [
      "lmbstudio"
    ],
    "list_album": [
      {
        "id_album": "2059014002",
        "link_thumb": "https://live.staticflickr.com/65535/51787465483_4162c47bf0_o.gif",
        "title": "Dragon Art_L5"
      }
    ]
  },
  {
    "author": "LMB Studio",
    "link_thumb": "https://live.staticflickr.com/65535/51786397482_e155011ef9_o.gif",
    "link_bin": "https://github.com/lmbstudiocontact/mb5_30/raw/main/DragonArt_L5_366228270.bin",
    "id_bin": "DragonArt_L5_366228270",
    "list_language": [
      {
        "author": "LMB Studio",
        "link_thumb": "https://live.staticflickr.com/65535/51786397432_3717abe468_o.gif",
        "link_bin": "https://github.com/lmbstudiocontact/mb5_30/raw/main/DragonArt_L5_366228270_English.bin",
        "name_language": "English",
        "id_bin_language": "DragonArt_L5_366228270_English"
      },
      {
        "author": "LMB Studio",
        "link_thumb": "https://live.staticflickr.com/65535/51787465293_44a6ef15a9_o.gif",
        "link_bin": "https://github.com/lmbstudiocontact/mb5_30/raw/main/DragonArt_L5_366228270_Portuguese.bin",
        "name_language": "Portuguese",
        "id_bin_language": "DragonArt_L5_366228270_Portuguese"
      },
      {
        "author": "LMB Studio",
        "link_thumb": "https://live.staticflickr.com/65535/51786397327_56dbda99db_o.gif",
        "link_bin": "https://github.com/lmbstudiocontact/mb5_30/raw/main/DragonArt_L5_366228270_Russian.bin",
        "name_language": "Russian",
        "id_bin_language": "DragonArt_L5_366228270_Russian"
      },
      {
        "author": "LMB Studio",
        "link_thumb": "https://live.staticflickr.com/65535/51786397312_72eaf3edd0_o.gif",
        "link_bin": "https://github.com/lmbstudiocontact/mb5_30/raw/main/DragonArt_L5_366228270_Spanish.bin",
        "name_language": "Spanish",
        "id_bin_language": "DragonArt_L5_366228270_Spanish"
      }
    ],
    "array_tags": [
      "lmbstudio"
    ],
    "list_album": [
      {
        "id_album": "2059014002",
        "link_thumb": "https://live.staticflickr.com/65535/51786397482_e155011ef9_o.gif",
        "title": "Dragon Art_L5"
      }
    ]
  },
  {
    "author": "LMB Studio",
    "link_thumb": "https://live.staticflickr.com/65535/51788080340_c4c5784493_o.gif",
    "link_bin": "https://github.com/lmbstudiocontact/mb5_30/raw/main/DragonBallAnime_L2_-1048564556.bin",
    "id_bin": "DragonBallAnime_L2_-1048564556",
    "list_language": [
      {
        "author": "LMB Studio",
        "link_thumb": "https://live.staticflickr.com/65535/51787830844_a9389fba67_o.gif",
        "link_bin": "https://github.com/lmbstudiocontact/mb5_30/raw/main/DragonBallAnime_L2_-1048564556_English.bin",
        "name_language": "English",
        "id_bin_language": "DragonBallAnime_L2_-1048564556_English"
      },
      {
        "author": "LMB Studio",
        "link_thumb": "https://live.staticflickr.com/65535/51787830799_9e67643252_o.gif",
        "link_bin": "https://github.com/lmbstudiocontact/mb5_30/raw/main/DragonBallAnime_L2_-1048564556_Portuguese.bin",
        "name_language": "Portuguese",
        "id_bin_language": "DragonBallAnime_L2_-1048564556_Portuguese"
      },
      {
        "author": "LMB Studio",
        "link_thumb": "https://live.staticflickr.com/65535/51787457848_c665509e7f_o.gif",
        "link_bin": "https://github.com/lmbstudiocontact/mb5_30/raw/main/DragonBallAnime_L2_-1048564556_Russian.bin",
        "name_language": "Russian",
        "id_bin_language": "DragonBallAnime_L2_-1048564556_Russian"
      },
      {
        "author": "LMB Studio",
        "link_thumb": "https://live.staticflickr.com/65535/51787830719_9794d40c4a_o.gif",
        "link_bin": "https://github.com/lmbstudiocontact/mb5_30/raw/main/DragonBallAnime_L2_-1048564556_Spanish.bin",
        "name_language": "Spanish",
        "id_bin_language": "DragonBallAnime_L2_-1048564556_Spanish"
      }
    ],
    "array_tags": [
      "lmbstudio"
    ],
    "list_album": [
      {
        "id_album": "1464725221",
        "link_thumb": "https://live.staticflickr.com/65535/51788080340_c4c5784493_o.gif",
        "title": "Dragon Ball Anime_L2"
      }
    ]
  },
  {
    "author": "LMB Studio",
    "link_thumb": "https://live.staticflickr.com/65535/51788080065_dd8e416ced_o.gif",
    "link_bin": "https://github.com/lmbstudiocontact/mb5_30/raw/main/DragonBallAnime_L2_-1048564557.bin",
    "id_bin": "DragonBallAnime_L2_-1048564557",
    "list_language": [
      {
        "author": "LMB Studio",
        "link_thumb": "https://live.staticflickr.com/65535/51786390277_d59a9366ed_o.gif",
        "link_bin": "https://github.com/lmbstudiocontact/mb5_30/raw/main/DragonBallAnime_L2_-1048564557_English.bin",
        "name_language": "English",
        "id_bin_language": "DragonBallAnime_L2_-1048564557_English"
      },
      {
        "author": "LMB Studio",
        "link_thumb": "https://live.staticflickr.com/65535/51787830639_4213052c2d_o.gif",
        "link_bin": "https://github.com/lmbstudiocontact/mb5_30/raw/main/DragonBallAnime_L2_-1048564557_Portuguese.bin",
        "name_language": "Portuguese",
        "id_bin_language": "DragonBallAnime_L2_-1048564557_Portuguese"
      },
      {
        "author": "LMB Studio",
        "link_thumb": "https://live.staticflickr.com/65535/51787457643_107e85e8f5_o.gif",
        "link_bin": "https://github.com/lmbstudiocontact/mb5_30/raw/main/DragonBallAnime_L2_-1048564557_Russian.bin",
        "name_language": "Russian",
        "id_bin_language": "DragonBallAnime_L2_-1048564557_Russian"
      },
      {
        "author": "LMB Studio",
        "link_thumb": "https://live.staticflickr.com/65535/51787457613_38e7e56e2e_o.gif",
        "link_bin": "https://github.com/lmbstudiocontact/mb5_30/raw/main/DragonBallAnime_L2_-1048564557_Spanish.bin",
        "name_language": "Spanish",
        "id_bin_language": "DragonBallAnime_L2_-1048564557_Spanish"
      }
    ],
    "array_tags": [
      "lmbstudio"
    ],
    "list_album": [
      {
        "id_album": "1464725221",
        "link_thumb": "https://live.staticflickr.com/65535/51788080065_dd8e416ced_o.gif",
        "title": "Dragon Ball Anime_L2"
      }
    ]
  },
  {
    "author": "LMB Studio",
    "link_thumb": "https://live.staticflickr.com/65535/51786390112_39a7bed78d_o.gif",
    "link_bin": "https://github.com/lmbstudiocontact/mb5_30/raw/main/DragonBallAnime_L2_-1116432698.bin",
    "id_bin": "DragonBallAnime_L2_-1116432698",
    "list_language": [
      {
        "author": "LMB Studio",
        "link_thumb": "https://live.staticflickr.com/65535/51786390077_0cd9f77a32_o.gif",
        "link_bin": "https://github.com/lmbstudiocontact/mb5_30/raw/main/DragonBallAnime_L2_-1116432698_English.bin",
        "name_language": "English",
        "id_bin_language": "DragonBallAnime_L2_-1116432698_English"
      },
      {
        "author": "LMB Studio",
        "link_thumb": "https://live.staticflickr.com/65535/51787457518_d35673b89c_o.gif",
        "link_bin": "https://github.com/lmbstudiocontact/mb5_30/raw/main/DragonBallAnime_L2_-1116432698_Portuguese.bin",
        "name_language": "Portuguese",
        "id_bin_language": "DragonBallAnime_L2_-1116432698_Portuguese"
      },
      {
        "author": "LMB Studio",
        "link_thumb": "https://live.staticflickr.com/65535/51786390007_9eec4c3da3_o.gif",
        "link_bin": "https://github.com/lmbstudiocontact/mb5_30/raw/main/DragonBallAnime_L2_-1116432698_Russian.bin",
        "name_language": "Russian",
        "id_bin_language": "DragonBallAnime_L2_-1116432698_Russian"
      },
      {
        "author": "LMB Studio",
        "link_thumb": "https://live.staticflickr.com/65535/51787208126_9e2ed6672f_o.gif",
        "link_bin": "https://github.com/lmbstudiocontact/mb5_30/raw/main/DragonBallAnime_L2_-1116432698_Spanish.bin",
        "name_language": "Spanish",
        "id_bin_language": "DragonBallAnime_L2_-1116432698_Spanish"
      }
    ],
    "array_tags": [
      "lmbstudio"
    ],
    "list_album": [
      {
        "id_album": "1464725221",
        "link_thumb": "https://live.staticflickr.com/65535/51786390112_39a7bed78d_o.gif",
        "title": "Dragon Ball Anime_L2"
      }
    ]
  },
  {
    "author": "LMB Studio",
    "link_thumb": "https://live.staticflickr.com/65535/51787208096_5e00275f02_o.gif",
    "link_bin": "https://github.com/lmbstudiocontact/mb5_30/raw/main/DragonBallAnime_L2_-1182179044.bin",
    "id_bin": "DragonBallAnime_L2_-1182179044",
    "list_language": [
      {
        "author": "LMB Studio",
        "link_thumb": "https://live.staticflickr.com/65535/51787830244_8d152b917f_o.gif",
        "link_bin": "https://github.com/lmbstudiocontact/mb5_30/raw/main/DragonBallAnime_L2_-1182179044_English.bin",
        "name_language": "English",
        "id_bin_language": "DragonBallAnime_L2_-1182179044_English"
      },
      {
        "author": "LMB Studio",
        "link_thumb": "https://live.staticflickr.com/65535/51788079510_1aa47ddda9_o.gif",
        "link_bin": "https://github.com/lmbstudiocontact/mb5_30/raw/main/DragonBallAnime_L2_-1182179044_Portuguese.bin",
        "name_language": "Portuguese",
        "id_bin_language": "DragonBallAnime_L2_-1182179044_Portuguese"
      },
      {
        "author": "LMB Studio",
        "link_thumb": "https://live.staticflickr.com/65535/51788079475_6055f615a5_o.gif",
        "link_bin": "https://github.com/lmbstudiocontact/mb5_30/raw/main/DragonBallAnime_L2_-1182179044_Russian.bin",
        "name_language": "Russian",
        "id_bin_language": "DragonBallAnime_L2_-1182179044_Russian"
      },
      {
        "author": "LMB Studio",
        "link_thumb": "https://live.staticflickr.com/65535/51788079440_21cf21efaa_o.gif",
        "link_bin": "https://github.com/lmbstudiocontact/mb5_30/raw/main/DragonBallAnime_L2_-1182179044_Spanish.bin",
        "name_language": "Spanish",
        "id_bin_language": "DragonBallAnime_L2_-1182179044_Spanish"
      }
    ],
    "array_tags": [
      "lmbstudio"
    ],
    "list_album": [
      {
        "id_album": "1464725221",
        "link_thumb": "https://live.staticflickr.com/65535/51787208096_5e00275f02_o.gif",
        "title": "Dragon Ball Anime_L2"
      }
    ]
  },
  {
    "author": "LMB Studio",
    "link_thumb": "https://live.staticflickr.com/65535/51787207871_0da7351803_o.gif",
    "link_bin": "https://github.com/lmbstudiocontact/mb5_30/raw/main/DragonBallAnime_L2_-1182179045.bin",
    "id_bin": "DragonBallAnime_L2_-1182179045",
    "list_language": [
      {
        "author": "LMB Studio",
        "link_thumb": "https://live.staticflickr.com/65535/51786389607_160bef0bbb_o.gif",
        "link_bin": "https://github.com/lmbstudiocontact/mb5_30/raw/main/DragonBallAnime_L2_-1182179045_English.bin",
        "name_language": "English",
        "id_bin_language": "DragonBallAnime_L2_-1182179045_English"
      },
      {
        "author": "LMB Studio",
        "link_thumb": "https://live.staticflickr.com/65535/51787457063_55674205dc_o.gif",
        "link_bin": "https://github.com/lmbstudiocontact/mb5_30/raw/main/DragonBallAnime_L2_-1182179045_Portuguese.bin",
        "name_language": "Portuguese",
        "id_bin_language": "DragonBallAnime_L2_-1182179045_Portuguese"
      },
      {
        "author": "LMB Studio",
        "link_thumb": "https://live.staticflickr.com/65535/51787457023_67f067dd56_o.gif",
        "link_bin": "https://github.com/lmbstudiocontact/mb5_30/raw/main/DragonBallAnime_L2_-1182179045_Russian.bin",
        "name_language": "Russian",
        "id_bin_language": "DragonBallAnime_L2_-1182179045_Russian"
      },
      {
        "author": "LMB Studio",
        "link_thumb": "https://live.staticflickr.com/65535/51787207711_f6ee0a7d6d_o.gif",
        "link_bin": "https://github.com/lmbstudiocontact/mb5_30/raw/main/DragonBallAnime_L2_-1182179045_Spanish.bin",
        "name_language": "Spanish",
        "id_bin_language": "DragonBallAnime_L2_-1182179045_Spanish"
      }
    ],
    "array_tags": [
      "lmbstudio"
    ],
    "list_album": [
      {
        "id_album": "1464725221",
        "link_thumb": "https://live.staticflickr.com/65535/51787207871_0da7351803_o.gif",
        "title": "Dragon Ball Anime_L2"
      }
    ]
  },
  {
    "author": "LMB Studio",
    "link_thumb": "https://live.staticflickr.com/65535/51786394097_59bda86bcf_o.gif",
    "link_bin": "https://github.com/lmbstudiocontact/mb5_30/raw/main/DragonBallAnime_L2_-124143945.bin",
    "id_bin": "DragonBallAnime_L2_-124143945",
    "list_language": [
      {
        "author": "LMB Studio",
        "link_thumb": "https://live.staticflickr.com/65535/51787212166_0e35ebdee0_o.gif",
        "link_bin": "https://github.com/lmbstudiocontact/mb5_30/raw/main/DragonBallAnime_L2_-124143945_English.bin",
        "name_language": "English",
        "id_bin_language": "DragonBallAnime_L2_-124143945_English"
      },
      {
        "author": "LMB Studio",
        "link_thumb": "https://live.staticflickr.com/65535/51788084080_8296a55ac6_o.gif",
        "link_bin": "https://github.com/lmbstudiocontact/mb5_30/raw/main/DragonBallAnime_L2_-124143945_Portuguese.bin",
        "name_language": "Portuguese",
        "id_bin_language": "DragonBallAnime_L2_-124143945_Portuguese"
      },
      {
        "author": "LMB Studio",
        "link_thumb": "https://live.staticflickr.com/65535/51786394032_8ef8a86a04_o.gif",
        "link_bin": "https://github.com/lmbstudiocontact/mb5_30/raw/main/DragonBallAnime_L2_-124143945_Russian.bin",
        "name_language": "Russian",
        "id_bin_language": "DragonBallAnime_L2_-124143945_Russian"
      },
      {
        "author": "LMB Studio",
        "link_thumb": "https://live.staticflickr.com/65535/51787461728_07c7eb68c9_o.gif",
        "link_bin": "https://github.com/lmbstudiocontact/mb5_30/raw/main/DragonBallAnime_L2_-124143945_Spanish.bin",
        "name_language": "Spanish",
        "id_bin_language": "DragonBallAnime_L2_-124143945_Spanish"
      }
    ],
    "array_tags": [
      "lmbstudio"
    ],
    "list_album": [
      {
        "id_album": "1464725221",
        "link_thumb": "https://live.staticflickr.com/65535/51786394097_59bda86bcf_o.gif",
        "title": "Dragon Ball Anime_L2"
      }
    ]
  },
  {
    "author": "LMB Studio",
    "link_thumb": "https://live.staticflickr.com/65535/51786389322_be03eba63b_o.gif",
    "link_bin": "https://github.com/lmbstudiocontact/mb5_30/raw/main/DragonBallAnime_L2_-1272959298.bin",
    "id_bin": "DragonBallAnime_L2_-1272959298",
    "list_language": [
      {
        "author": "LMB Studio",
        "link_thumb": "https://live.staticflickr.com/65535/51787829699_a9243a7c43_o.gif",
        "link_bin": "https://github.com/lmbstudiocontact/mb5_30/raw/main/DragonBallAnime_L2_-1272959298_English.bin",
        "name_language": "English",
        "id_bin_language": "DragonBallAnime_L2_-1272959298_English"
      },
      {
        "author": "LMB Studio",
        "link_thumb": "https://live.staticflickr.com/65535/51787207451_3be59aa591_o.gif",
        "link_bin": "https://github.com/lmbstudiocontact/mb5_30/raw/main/DragonBallAnime_L2_-1272959298_Portuguese.bin",
        "name_language": "Portuguese",
        "id_bin_language": "DragonBallAnime_L2_-1272959298_Portuguese"
      },
      {
        "author": "LMB Studio",
        "link_thumb": "https://live.staticflickr.com/65535/51786389207_e7dd6855c8_o.gif",
        "link_bin": "https://github.com/lmbstudiocontact/mb5_30/raw/main/DragonBallAnime_L2_-1272959298_Russian.bin",
        "name_language": "Russian",
        "id_bin_language": "DragonBallAnime_L2_-1272959298_Russian"
      },
      {
        "author": "LMB Studio",
        "link_thumb": "https://live.staticflickr.com/65535/51787456623_fd12136384_o.gif",
        "link_bin": "https://github.com/lmbstudiocontact/mb5_30/raw/main/DragonBallAnime_L2_-1272959298_Spanish.bin",
        "name_language": "Spanish",
        "id_bin_language": "DragonBallAnime_L2_-1272959298_Spanish"
      }
    ],
    "array_tags": [
      "lmbstudio"
    ],
    "list_album": [
      {
        "id_album": "1464725221",
        "link_thumb": "https://live.staticflickr.com/65535/51786389322_be03eba63b_o.gif",
        "title": "Dragon Ball Anime_L2"
      }
    ]
  },
  {
    "author": "LMB Studio",
    "link_thumb": "https://live.staticflickr.com/65535/51788078905_a1d8c24b11_o.gif",
    "link_bin": "https://github.com/lmbstudiocontact/mb5_30/raw/main/DragonBallAnime_L2_-1272959299.bin",
    "id_bin": "DragonBallAnime_L2_-1272959299",
    "list_language": [
      {
        "author": "LMB Studio",
        "link_thumb": "https://live.staticflickr.com/65535/51786389127_4fdf47e068_o.gif",
        "link_bin": "https://github.com/lmbstudiocontact/mb5_30/raw/main/DragonBallAnime_L2_-1272959299_English.bin",
        "name_language": "English",
        "id_bin_language": "DragonBallAnime_L2_-1272959299_English"
      },
      {
        "author": "LMB Studio",
        "link_thumb": "https://live.staticflickr.com/65535/51787829509_7b6244ae41_o.gif",
        "link_bin": "https://github.com/lmbstudiocontact/mb5_30/raw/main/DragonBallAnime_L2_-1272959299_Portuguese.bin",
        "name_language": "Portuguese",
        "id_bin_language": "DragonBallAnime_L2_-1272959299_Portuguese"
      },
      {
        "author": "LMB Studio",
        "link_thumb": "https://live.staticflickr.com/65535/51787456478_ded97980ca_o.gif",
        "link_bin": "https://github.com/lmbstudiocontact/mb5_30/raw/main/DragonBallAnime_L2_-1272959299_Russian.bin",
        "name_language": "Russian",
        "id_bin_language": "DragonBallAnime_L2_-1272959299_Russian"
      },
      {
        "author": "LMB Studio",
        "link_thumb": "https://live.staticflickr.com/65535/51787207206_b7a56265f5_o.gif",
        "link_bin": "https://github.com/lmbstudiocontact/mb5_30/raw/main/DragonBallAnime_L2_-1272959299_Spanish.bin",
        "name_language": "Spanish",
        "id_bin_language": "DragonBallAnime_L2_-1272959299_Spanish"
      }
    ],
    "array_tags": [
      "lmbstudio"
    ],
    "list_album": [
      {
        "id_album": "1464725221",
        "link_thumb": "https://live.staticflickr.com/65535/51788078905_a1d8c24b11_o.gif",
        "title": "Dragon Ball Anime_L2"
      }
    ]
  },
  {
    "author": "LMB Studio",
    "link_thumb": "https://live.staticflickr.com/65535/51787829399_27b64cb4fb_o.gif",
    "link_bin": "https://github.com/lmbstudiocontact/mb5_30/raw/main/DragonBallAnime_L2_-1272959300.bin",
    "id_bin": "DragonBallAnime_L2_-1272959300",
    "list_language": [
      {
        "author": "LMB Studio",
        "link_thumb": "https://live.staticflickr.com/65535/51787829364_512281bc6c_o.gif",
        "link_bin": "https://github.com/lmbstudiocontact/mb5_30/raw/main/DragonBallAnime_L2_-1272959300_English.bin",
        "name_language": "English",
        "id_bin_language": "DragonBallAnime_L2_-1272959300_English"
      },
      {
        "author": "LMB Studio",
        "link_thumb": "https://live.staticflickr.com/65535/51788078610_bdb105c4da_o.gif",
        "link_bin": "https://github.com/lmbstudiocontact/mb5_30/raw/main/DragonBallAnime_L2_-1272959300_Portuguese.bin",
        "name_language": "Portuguese",
        "id_bin_language": "DragonBallAnime_L2_-1272959300_Portuguese"
      },
      {
        "author": "LMB Studio",
        "link_thumb": "https://live.staticflickr.com/65535/51787829304_4d6ef6dd82_o.gif",
        "link_bin": "https://github.com/lmbstudiocontact/mb5_30/raw/main/DragonBallAnime_L2_-1272959300_Russian.bin",
        "name_language": "Russian",
        "id_bin_language": "DragonBallAnime_L2_-1272959300_Russian"
      },
      {
        "author": "LMB Studio",
        "link_thumb": "https://live.staticflickr.com/65535/51787829239_cffe0cd448_o.gif",
        "link_bin": "https://github.com/lmbstudiocontact/mb5_30/raw/main/DragonBallAnime_L2_-1272959300_Spanish.bin",
        "name_language": "Spanish",
        "id_bin_language": "DragonBallAnime_L2_-1272959300_Spanish"
      }
    ],
    "array_tags": [
      "lmbstudio"
    ],
    "list_album": [
      {
        "id_album": "1464725221",
        "link_thumb": "https://live.staticflickr.com/65535/51787829399_27b64cb4fb_o.gif",
        "title": "Dragon Ball Anime_L2"
      }
    ]
  },
  {
    "author": "LMB Studio",
    "link_thumb": "https://live.staticflickr.com/65535/51787207036_323537f5a0_o.gif",
    "link_bin": "https://github.com/lmbstudiocontact/mb5_30/raw/main/DragonBallAnime_L2_-1272959301.bin",
    "id_bin": "DragonBallAnime_L2_-1272959301",
    "list_language": [
      {
        "author": "LMB Studio",
        "link_thumb": "https://live.staticflickr.com/65535/51786388802_1ea7defb84_o.gif",
        "link_bin": "https://github.com/lmbstudiocontact/mb5_30/raw/main/DragonBallAnime_L2_-1272959301_English.bin",
        "name_language": "English",
        "id_bin_language": "DragonBallAnime_L2_-1272959301_English"
      },
      {
        "author": "LMB Studio",
        "link_thumb": "https://live.staticflickr.com/65535/51786388732_54aba784f7_o.gif",
        "link_bin": "https://github.com/lmbstudiocontact/mb5_30/raw/main/DragonBallAnime_L2_-1272959301_Portuguese.bin",
        "name_language": "Portuguese",
        "id_bin_language": "DragonBallAnime_L2_-1272959301_Portuguese"
      },
      {
        "author": "LMB Studio",
        "link_thumb": "https://live.staticflickr.com/65535/51787456148_7c51a28136_o.gif",
        "link_bin": "https://github.com/lmbstudiocontact/mb5_30/raw/main/DragonBallAnime_L2_-1272959301_Russian.bin",
        "name_language": "Russian",
        "id_bin_language": "DragonBallAnime_L2_-1272959301_Russian"
      },
      {
        "author": "LMB Studio",
        "link_thumb": "https://live.staticflickr.com/65535/51787206866_beaab2eb2e_o.gif",
        "link_bin": "https://github.com/lmbstudiocontact/mb5_30/raw/main/DragonBallAnime_L2_-1272959301_Spanish.bin",
        "name_language": "Spanish",
        "id_bin_language": "DragonBallAnime_L2_-1272959301_Spanish"
      }
    ],
    "array_tags": [
      "lmbstudio"
    ],
    "list_album": [
      {
        "id_album": "1464725221",
        "link_thumb": "https://live.staticflickr.com/65535/51787207036_323537f5a0_o.gif",
        "title": "Dragon Ball Anime_L2"
      }
    ]
  },
  {
    "author": "LMB Studio",
    "link_thumb": "https://live.staticflickr.com/65535/51786388642_080ed12c57_o.gif",
    "link_bin": "https://github.com/lmbstudiocontact/mb5_30/raw/main/DragonBallAnime_L2_-1272959302.bin",
    "id_bin": "DragonBallAnime_L2_-1272959302",
    "list_language": [
      {
        "author": "LMB Studio",
        "link_thumb": "https://live.staticflickr.com/65535/51787829019_26ba9c5fe8_o.gif",
        "link_bin": "https://github.com/lmbstudiocontact/mb5_30/raw/main/DragonBallAnime_L2_-1272959302_English.bin",
        "name_language": "English",
        "id_bin_language": "DragonBallAnime_L2_-1272959302_English"
      },
      {
        "author": "LMB Studio",
        "link_thumb": "https://live.staticflickr.com/65535/51787206706_7987de577d_o.gif",
        "link_bin": "https://github.com/lmbstudiocontact/mb5_30/raw/main/DragonBallAnime_L2_-1272959302_Portuguese.bin",
        "name_language": "Portuguese",
        "id_bin_language": "DragonBallAnime_L2_-1272959302_Portuguese"
      },
      {
        "author": "LMB Studio",
        "link_thumb": "https://live.staticflickr.com/65535/51786388502_354702bb9f_o.gif",
        "link_bin": "https://github.com/lmbstudiocontact/mb5_30/raw/main/DragonBallAnime_L2_-1272959302_Russian.bin",
        "name_language": "Russian",
        "id_bin_language": "DragonBallAnime_L2_-1272959302_Russian"
      },
      {
        "author": "LMB Studio",
        "link_thumb": "https://live.staticflickr.com/65535/51787455943_d26fb90147_o.gif",
        "link_bin": "https://github.com/lmbstudiocontact/mb5_30/raw/main/DragonBallAnime_L2_-1272959302_Spanish.bin",
        "name_language": "Spanish",
        "id_bin_language": "DragonBallAnime_L2_-1272959302_Spanish"
      }
    ],
    "array_tags": [
      "lmbstudio"
    ],
    "list_album": [
      {
        "id_album": "1464725221",
        "link_thumb": "https://live.staticflickr.com/65535/51786388642_080ed12c57_o.gif",
        "title": "Dragon Ball Anime_L2"
      }
    ]
  },
  {
    "author": "LMB Studio",
    "link_thumb": "https://live.staticflickr.com/65535/51787827504_7b1ae2edb8_o.gif",
    "link_bin": "https://github.com/lmbstudiocontact/mb5_30/raw/main/DragonBallAnime_L2_-1433070426.bin",
    "id_bin": "DragonBallAnime_L2_-1433070426",
    "list_language": [
      {
        "author": "LMB Studio",
        "link_thumb": "https://live.staticflickr.com/65535/51787454598_0deeaa5cd1_o.gif",
        "link_bin": "https://github.com/lmbstudiocontact/mb5_30/raw/main/DragonBallAnime_L2_-1433070426_English.bin",
        "name_language": "English",
        "id_bin_language": "DragonBallAnime_L2_-1433070426_English"
      },
      {
        "author": "LMB Studio",
        "link_thumb": "https://live.staticflickr.com/65535/51786387177_093d118deb_o.gif",
        "link_bin": "https://github.com/lmbstudiocontact/mb5_30/raw/main/DragonBallAnime_L2_-1433070426_Portuguese.bin",
        "name_language": "Portuguese",
        "id_bin_language": "DragonBallAnime_L2_-1433070426_Portuguese"
      },
      {
        "author": "LMB Studio",
        "link_thumb": "https://live.staticflickr.com/65535/51787205136_5e233cc5ee_o.gif",
        "link_bin": "https://github.com/lmbstudiocontact/mb5_30/raw/main/DragonBallAnime_L2_-1433070426_Russian.bin",
        "name_language": "Russian",
        "id_bin_language": "DragonBallAnime_L2_-1433070426_Russian"
      },
      {
        "author": "LMB Studio",
        "link_thumb": "https://live.staticflickr.com/65535/51786387102_a9096ffcc2_o.gif",
        "link_bin": "https://github.com/lmbstudiocontact/mb5_30/raw/main/DragonBallAnime_L2_-1433070426_Spanish.bin",
        "name_language": "Spanish",
        "id_bin_language": "DragonBallAnime_L2_-1433070426_Spanish"
      }
    ],
    "array_tags": [
      "lmbstudio"
    ],
    "list_album": [
      {
        "id_album": "1464725221",
        "link_thumb": "https://live.staticflickr.com/65535/51787827504_7b1ae2edb8_o.gif",
        "title": "Dragon Ball Anime_L2"
      }
    ]
  },
  {
    "author": "LMB Studio",
    "link_thumb": "https://live.staticflickr.com/65535/51788076170_194fc22980_o.gif",
    "link_bin": "https://github.com/lmbstudiocontact/mb5_30/raw/main/DragonBallAnime_L2_-1678843112.bin",
    "id_bin": "DragonBallAnime_L2_-1678843112",
    "list_language": [
      {
        "author": "LMB Studio",
        "link_thumb": "https://live.staticflickr.com/65535/51787453818_83981ba58e_o.gif",
        "link_bin": "https://github.com/lmbstudiocontact/mb5_30/raw/main/DragonBallAnime_L2_-1678843112_English.bin",
        "name_language": "English",
        "id_bin_language": "DragonBallAnime_L2_-1678843112_English"
      },
      {
        "author": "LMB Studio",
        "link_thumb": "https://live.staticflickr.com/65535/51786386412_da217b8610_o.gif",
        "link_bin": "https://github.com/lmbstudiocontact/mb5_30/raw/main/DragonBallAnime_L2_-1678843112_Portuguese.bin",
        "name_language": "Portuguese",
        "id_bin_language": "DragonBallAnime_L2_-1678843112_Portuguese"
      },
      {
        "author": "LMB Studio",
        "link_thumb": "https://live.staticflickr.com/65535/51787826699_ff4c5d5b2b_o.gif",
        "link_bin": "https://github.com/lmbstudiocontact/mb5_30/raw/main/DragonBallAnime_L2_-1678843112_Russian.bin",
        "name_language": "Russian",
        "id_bin_language": "DragonBallAnime_L2_-1678843112_Russian"
      },
      {
        "author": "LMB Studio",
        "link_thumb": "https://live.staticflickr.com/65535/51787453678_5fd078f2b6_o.gif",
        "link_bin": "https://github.com/lmbstudiocontact/mb5_30/raw/main/DragonBallAnime_L2_-1678843112_Spanish.bin",
        "name_language": "Spanish",
        "id_bin_language": "DragonBallAnime_L2_-1678843112_Spanish"
      }
    ],
    "array_tags": [
      "lmbstudio"
    ],
    "list_album": [
      {
        "id_album": "1464725221",
        "link_thumb": "https://live.staticflickr.com/65535/51788076170_194fc22980_o.gif",
        "title": "Dragon Ball Anime_L2"
      }
    ]
  },
  {
    "author": "LMB Studio",
    "link_thumb": "https://live.staticflickr.com/65535/51788075980_b17226e13c_o.gif",
    "link_bin": "https://github.com/lmbstudiocontact/mb5_30/raw/main/DragonBallAnime_L2_-1678843113.bin",
    "id_bin": "DragonBallAnime_L2_-1678843113",
    "list_language": [
      {
        "author": "LMB Studio",
        "link_thumb": "https://live.staticflickr.com/65535/51788075935_ce795950aa_o.gif",
        "link_bin": "https://github.com/lmbstudiocontact/mb5_30/raw/main/DragonBallAnime_L2_-1678843113_English.bin",
        "name_language": "English",
        "id_bin_language": "DragonBallAnime_L2_-1678843113_English"
      },
      {
        "author": "LMB Studio",
        "link_thumb": "https://live.staticflickr.com/65535/51786386217_eb3896b8d9_o.gif",
        "link_bin": "https://github.com/lmbstudiocontact/mb5_30/raw/main/DragonBallAnime_L2_-1678843113_Portuguese.bin",
        "name_language": "Portuguese",
        "id_bin_language": "DragonBallAnime_L2_-1678843113_Portuguese"
      },
      {
        "author": "LMB Studio",
        "link_thumb": "https://live.staticflickr.com/65535/51787826509_51e5a704da_o.gif",
        "link_bin": "https://github.com/lmbstudiocontact/mb5_30/raw/main/DragonBallAnime_L2_-1678843113_Russian.bin",
        "name_language": "Russian",
        "id_bin_language": "DragonBallAnime_L2_-1678843113_Russian"
      },
      {
        "author": "LMB Studio",
        "link_thumb": "https://live.staticflickr.com/65535/51787826474_64e72f71cb_o.gif",
        "link_bin": "https://github.com/lmbstudiocontact/mb5_30/raw/main/DragonBallAnime_L2_-1678843113_Spanish.bin",
        "name_language": "Spanish",
        "id_bin_language": "DragonBallAnime_L2_-1678843113_Spanish"
      }
    ],
    "array_tags": [
      "lmbstudio"
    ],
    "list_album": [
      {
        "id_album": "1464725221",
        "link_thumb": "https://live.staticflickr.com/65535/51788075980_b17226e13c_o.gif",
        "title": "Dragon Ball Anime_L2"
      }
    ]
  },
  {
    "author": "LMB Studio",
    "link_thumb": "https://live.staticflickr.com/65535/51787826299_a984666a16_o.gif",
    "link_bin": "https://github.com/lmbstudiocontact/mb5_30/raw/main/DragonBallAnime_L2_-1729118260.bin",
    "id_bin": "DragonBallAnime_L2_-1729118260",
    "list_language": [
      {
        "author": "LMB Studio",
        "link_thumb": "https://live.staticflickr.com/65535/51788075615_7e1fe02b0f_o.gif",
        "link_bin": "https://github.com/lmbstudiocontact/mb5_30/raw/main/DragonBallAnime_L2_-1729118260_English.bin",
        "name_language": "English",
        "id_bin_language": "DragonBallAnime_L2_-1729118260_English"
      },
      {
        "author": "LMB Studio",
        "link_thumb": "https://live.staticflickr.com/65535/51787203956_b4fbb1d5e5_o.gif",
        "link_bin": "https://github.com/lmbstudiocontact/mb5_30/raw/main/DragonBallAnime_L2_-1729118260_Portuguese.bin",
        "name_language": "Portuguese",
        "id_bin_language": "DragonBallAnime_L2_-1729118260_Portuguese"
      },
      {
        "author": "LMB Studio",
        "link_thumb": "https://live.staticflickr.com/65535/51788075550_4c71358d45_o.gif",
        "link_bin": "https://github.com/lmbstudiocontact/mb5_30/raw/main/DragonBallAnime_L2_-1729118260_Russian.bin",
        "name_language": "Russian",
        "id_bin_language": "DragonBallAnime_L2_-1729118260_Russian"
      },
      {
        "author": "LMB Studio",
        "link_thumb": "https://live.staticflickr.com/65535/51786385877_247c964abc_o.gif",
        "link_bin": "https://github.com/lmbstudiocontact/mb5_30/raw/main/DragonBallAnime_L2_-1729118260_Spanish.bin",
        "name_language": "Spanish",
        "id_bin_language": "DragonBallAnime_L2_-1729118260_Spanish"
      }
    ],
    "array_tags": [
      "lmbstudio"
    ],
    "list_album": [
      {
        "id_album": "1464725221",
        "link_thumb": "https://live.staticflickr.com/65535/51787826299_a984666a16_o.gif",
        "title": "Dragon Ball Anime_L2"
      }
    ]
  },
  {
    "author": "LMB Studio",
    "link_thumb": "https://live.staticflickr.com/65535/51787453173_eea1c4ded2_o.gif",
    "link_bin": "https://github.com/lmbstudiocontact/mb5_30/raw/main/DragonBallAnime_L2_-1896669822.bin",
    "id_bin": "DragonBallAnime_L2_-1896669822",
    "list_language": [
      {
        "author": "LMB Studio",
        "link_thumb": "https://live.staticflickr.com/65535/51787453138_a260f53ecf_o.gif",
        "link_bin": "https://github.com/lmbstudiocontact/mb5_30/raw/main/DragonBallAnime_L2_-1896669822_English.bin",
        "name_language": "English",
        "id_bin_language": "DragonBallAnime_L2_-1896669822_English"
      },
      {
        "author": "LMB Studio",
        "link_thumb": "https://live.staticflickr.com/65535/51787453113_8d113b78d9_o.gif",
        "link_bin": "https://github.com/lmbstudiocontact/mb5_30/raw/main/DragonBallAnime_L2_-1896669822_Portuguese.bin",
        "name_language": "Portuguese",
        "id_bin_language": "DragonBallAnime_L2_-1896669822_Portuguese"
      },
      {
        "author": "LMB Studio",
        "link_thumb": "https://live.staticflickr.com/65535/51786385767_7ba4a7d0ce_o.gif",
        "link_bin": "https://github.com/lmbstudiocontact/mb5_30/raw/main/DragonBallAnime_L2_-1896669822_Russian.bin",
        "name_language": "Russian",
        "id_bin_language": "DragonBallAnime_L2_-1896669822_Russian"
      },
      {
        "author": "LMB Studio",
        "link_thumb": "https://live.staticflickr.com/65535/51788075360_1f1b1930b4_o.gif",
        "link_bin": "https://github.com/lmbstudiocontact/mb5_30/raw/main/DragonBallAnime_L2_-1896669822_Spanish.bin",
        "name_language": "Spanish",
        "id_bin_language": "DragonBallAnime_L2_-1896669822_Spanish"
      }
    ],
    "array_tags": [
      "lmbstudio"
    ],
    "list_album": [
      {
        "id_album": "1464725221",
        "link_thumb": "https://live.staticflickr.com/65535/51787453173_eea1c4ded2_o.gif",
        "title": "Dragon Ball Anime_L2"
      }
    ]
  },
  {
    "author": "LMB Studio",
    "link_thumb": "https://live.staticflickr.com/65535/51787825984_42a3e8b4f1_o.gif",
    "link_bin": "https://github.com/lmbstudiocontact/mb5_30/raw/main/DragonBallAnime_L2_-1896669823.bin",
    "id_bin": "DragonBallAnime_L2_-1896669823",
    "list_language": [
      {
        "author": "LMB Studio",
        "link_thumb": "https://live.staticflickr.com/65535/51787452978_2977fabcb3_o.gif",
        "link_bin": "https://github.com/lmbstudiocontact/mb5_30/raw/main/DragonBallAnime_L2_-1896669823_English.bin",
        "name_language": "English",
        "id_bin_language": "DragonBallAnime_L2_-1896669823_English"
      },
      {
        "author": "LMB Studio",
        "link_thumb": "https://live.staticflickr.com/65535/51786385622_a536976d5b_o.gif",
        "link_bin": "https://github.com/lmbstudiocontact/mb5_30/raw/main/DragonBallAnime_L2_-1896669823_Portuguese.bin",
        "name_language": "Portuguese",
        "id_bin_language": "DragonBallAnime_L2_-1896669823_Portuguese"
      },
      {
        "author": "LMB Studio",
        "link_thumb": "https://live.staticflickr.com/65535/51787825819_897bf7f88d_o.gif",
        "link_bin": "https://github.com/lmbstudiocontact/mb5_30/raw/main/DragonBallAnime_L2_-1896669823_Russian.bin",
        "name_language": "Russian",
        "id_bin_language": "DragonBallAnime_L2_-1896669823_Russian"
      },
      {
        "author": "LMB Studio",
        "link_thumb": "https://live.staticflickr.com/65535/51788075175_632bb48bd6_o.gif",
        "link_bin": "https://github.com/lmbstudiocontact/mb5_30/raw/main/DragonBallAnime_L2_-1896669823_Spanish.bin",
        "name_language": "Spanish",
        "id_bin_language": "DragonBallAnime_L2_-1896669823_Spanish"
      }
    ],
    "array_tags": [
      "lmbstudio"
    ],
    "list_album": [
      {
        "id_album": "1464725221",
        "link_thumb": "https://live.staticflickr.com/65535/51787825984_42a3e8b4f1_o.gif",
        "title": "Dragon Ball Anime_L2"
      }
    ]
  },
  {
    "author": "LMB Studio",
    "link_thumb": "https://live.staticflickr.com/65535/51787452768_7dcb67acc8_o.gif",
    "link_bin": "https://github.com/lmbstudiocontact/mb5_30/raw/main/DragonBallAnime_L2_-1896669824.bin",
    "id_bin": "DragonBallAnime_L2_-1896669824",
    "list_language": [
      {
        "author": "LMB Studio",
        "link_thumb": "https://live.staticflickr.com/65535/51787825644_3884c848dd_o.gif",
        "link_bin": "https://github.com/lmbstudiocontact/mb5_30/raw/main/DragonBallAnime_L2_-1896669824_English.bin",
        "name_language": "English",
        "id_bin_language": "DragonBallAnime_L2_-1896669824_English"
      },
      {
        "author": "LMB Studio",
        "link_thumb": "https://live.staticflickr.com/65535/51787203456_bbec91981f_o.gif",
        "link_bin": "https://github.com/lmbstudiocontact/mb5_30/raw/main/DragonBallAnime_L2_-1896669824_Portuguese.bin",
        "name_language": "Portuguese",
        "id_bin_language": "DragonBallAnime_L2_-1896669824_Portuguese"
      },
      {
        "author": "LMB Studio",
        "link_thumb": "https://live.staticflickr.com/65535/51787825529_aa8867ab9f_o.gif",
        "link_bin": "https://github.com/lmbstudiocontact/mb5_30/raw/main/DragonBallAnime_L2_-1896669824_Russian.bin",
        "name_language": "Russian",
        "id_bin_language": "DragonBallAnime_L2_-1896669824_Russian"
      },
      {
        "author": "LMB Studio",
        "link_thumb": "https://live.staticflickr.com/65535/51786385282_47fe3e7080_o.gif",
        "link_bin": "https://github.com/lmbstudiocontact/mb5_30/raw/main/DragonBallAnime_L2_-1896669824_Spanish.bin",
        "name_language": "Spanish",
        "id_bin_language": "DragonBallAnime_L2_-1896669824_Spanish"
      }
    ],
    "array_tags": [
      "lmbstudio"
    ],
    "list_album": [
      {
        "id_album": "1464725221",
        "link_thumb": "https://live.staticflickr.com/65535/51787452768_7dcb67acc8_o.gif",
        "title": "Dragon Ball Anime_L2"
      }
    ]
  },
  {
    "author": "LMB Studio",
    "link_thumb": "https://live.staticflickr.com/65535/51787203261_e8222c1798_o.gif",
    "link_bin": "https://github.com/lmbstudiocontact/mb5_30/raw/main/DragonBallAnime_L2_-1896669846.bin",
    "id_bin": "DragonBallAnime_L2_-1896669846",
    "list_language": [
      {
        "author": "LMB Studio",
        "link_thumb": "https://live.staticflickr.com/65535/51786385227_bf0f1f2b08_o.gif",
        "link_bin": "https://github.com/lmbstudiocontact/mb5_30/raw/main/DragonBallAnime_L2_-1896669846_English.bin",
        "name_language": "English",
        "id_bin_language": "DragonBallAnime_L2_-1896669846_English"
      },
      {
        "author": "LMB Studio",
        "link_thumb": "https://live.staticflickr.com/65535/51787452458_f46a8dd23a_o.gif",
        "link_bin": "https://github.com/lmbstudiocontact/mb5_30/raw/main/DragonBallAnime_L2_-1896669846_Portuguese.bin",
        "name_language": "Portuguese",
        "id_bin_language": "DragonBallAnime_L2_-1896669846_Portuguese"
      },
      {
        "author": "LMB Studio",
        "link_thumb": "https://live.staticflickr.com/65535/51787825374_9838c5d815_o.gif",
        "link_bin": "https://github.com/lmbstudiocontact/mb5_30/raw/main/DragonBallAnime_L2_-1896669846_Russian.bin",
        "name_language": "Russian",
        "id_bin_language": "DragonBallAnime_L2_-1896669846_Russian"
      },
      {
        "author": "LMB Studio",
        "link_thumb": "https://live.staticflickr.com/65535/51786385047_9b133534ce_o.gif",
        "link_bin": "https://github.com/lmbstudiocontact/mb5_30/raw/main/DragonBallAnime_L2_-1896669846_Spanish.bin",
        "name_language": "Spanish",
        "id_bin_language": "DragonBallAnime_L2_-1896669846_Spanish"
      }
    ],
    "array_tags": [
      "lmbstudio"
    ],
    "list_album": [
      {
        "id_album": "1464725221",
        "link_thumb": "https://live.staticflickr.com/65535/51787203261_e8222c1798_o.gif",
        "title": "Dragon Ball Anime_L2"
      }
    ]
  },
  {
    "author": "LMB Studio",
    "link_thumb": "https://live.staticflickr.com/65535/51788074750_8514630c13_o.gif",
    "link_bin": "https://github.com/lmbstudiocontact/mb5_30/raw/main/DragonBallAnime_L2_-1896669847.bin",
    "id_bin": "DragonBallAnime_L2_-1896669847",
    "list_language": [
      {
        "author": "LMB Studio",
        "link_thumb": "https://live.staticflickr.com/65535/51786385002_ecbea6349f_o.gif",
        "link_bin": "https://github.com/lmbstudiocontact/mb5_30/raw/main/DragonBallAnime_L2_-1896669847_English.bin",
        "name_language": "English",
        "id_bin_language": "DragonBallAnime_L2_-1896669847_English"
      },
      {
        "author": "LMB Studio",
        "link_thumb": "https://live.staticflickr.com/65535/51787452263_84e196a6d0_o.gif",
        "link_bin": "https://github.com/lmbstudiocontact/mb5_30/raw/main/DragonBallAnime_L2_-1896669847_Portuguese.bin",
        "name_language": "Portuguese",
        "id_bin_language": "DragonBallAnime_L2_-1896669847_Portuguese"
      },
      {
        "author": "LMB Studio",
        "link_thumb": "https://live.staticflickr.com/65535/51787452238_9f615a1e29_o.gif",
        "link_bin": "https://github.com/lmbstudiocontact/mb5_30/raw/main/DragonBallAnime_L2_-1896669847_Russian.bin",
        "name_language": "Russian",
        "id_bin_language": "DragonBallAnime_L2_-1896669847_Russian"
      },
      {
        "author": "LMB Studio",
        "link_thumb": "https://live.staticflickr.com/65535/51788074650_2b4e412102_o.gif",
        "link_bin": "https://github.com/lmbstudiocontact/mb5_30/raw/main/DragonBallAnime_L2_-1896669847_Spanish.bin",
        "name_language": "Spanish",
        "id_bin_language": "DragonBallAnime_L2_-1896669847_Spanish"
      }
    ],
    "array_tags": [
      "lmbstudio"
    ],
    "list_album": [
      {
        "id_album": "1464725221",
        "link_thumb": "https://live.staticflickr.com/65535/51788074750_8514630c13_o.gif",
        "title": "Dragon Ball Anime_L2"
      }
    ]
  },
  {
    "author": "LMB Studio",
    "link_thumb": "https://live.staticflickr.com/65535/51786384877_3eb8699ae3_o.gif",
    "link_bin": "https://github.com/lmbstudiocontact/mb5_30/raw/main/DragonBallAnime_L2_-1897474211.bin",
    "id_bin": "DragonBallAnime_L2_-1897474211",
    "list_language": [
      {
        "author": "LMB Studio",
        "link_thumb": "https://live.staticflickr.com/65535/51787452188_23115f187c_o.gif",
        "link_bin": "https://github.com/lmbstudiocontact/mb5_30/raw/main/DragonBallAnime_L2_-1897474211_English.bin",
        "name_language": "English",
        "id_bin_language": "DragonBallAnime_L2_-1897474211_English"
      },
      {
        "author": "LMB Studio",
        "link_thumb": "https://live.staticflickr.com/65535/51787825094_fb35ed6a46_o.gif",
        "link_bin": "https://github.com/lmbstudiocontact/mb5_30/raw/main/DragonBallAnime_L2_-1897474211_Portuguese.bin",
        "name_language": "Portuguese",
        "id_bin_language": "DragonBallAnime_L2_-1897474211_Portuguese"
      },
      {
        "author": "LMB Studio",
        "link_thumb": "https://live.staticflickr.com/65535/51787202726_d747fe1227_o.gif",
        "link_bin": "https://github.com/lmbstudiocontact/mb5_30/raw/main/DragonBallAnime_L2_-1897474211_Russian.bin",
        "name_language": "Russian",
        "id_bin_language": "DragonBallAnime_L2_-1897474211_Russian"
      },
      {
        "author": "LMB Studio",
        "link_thumb": "https://live.staticflickr.com/65535/51787452068_260b0d7d5e_o.gif",
        "link_bin": "https://github.com/lmbstudiocontact/mb5_30/raw/main/DragonBallAnime_L2_-1897474211_Spanish.bin",
        "name_language": "Spanish",
        "id_bin_language": "DragonBallAnime_L2_-1897474211_Spanish"
      }
    ],
    "array_tags": [
      "lmbstudio"
    ],
    "list_album": [
      {
        "id_album": "1464725221",
        "link_thumb": "https://live.staticflickr.com/65535/51786384877_3eb8699ae3_o.gif",
        "title": "Dragon Ball Anime_L2"
      }
    ]
  },
  {
    "author": "LMB Studio",
    "link_thumb": "https://live.staticflickr.com/65535/51787461673_b48c89bc67_o.gif",
    "link_bin": "https://github.com/lmbstudiocontact/mb5_30/raw/main/DragonBallAnime_L2_-196522932.bin",
    "id_bin": "DragonBallAnime_L2_-196522932",
    "list_language": [
      {
        "author": "LMB Studio",
        "link_thumb": "https://live.staticflickr.com/65535/51786393922_3556d51378_o.gif",
        "link_bin": "https://github.com/lmbstudiocontact/mb5_30/raw/main/DragonBallAnime_L2_-196522932_English.bin",
        "name_language": "English",
        "id_bin_language": "DragonBallAnime_L2_-196522932_English"
      },
      {
        "author": "LMB Studio",
        "link_thumb": "https://live.staticflickr.com/65535/51787211996_4530930624_o.gif",
        "link_bin": "https://github.com/lmbstudiocontact/mb5_30/raw/main/DragonBallAnime_L2_-196522932_Portuguese.bin",
        "name_language": "Portuguese",
        "id_bin_language": "DragonBallAnime_L2_-196522932_Portuguese"
      },
      {
        "author": "LMB Studio",
        "link_thumb": "https://live.staticflickr.com/65535/51786393872_e0925692e5_o.gif",
        "link_bin": "https://github.com/lmbstudiocontact/mb5_30/raw/main/DragonBallAnime_L2_-196522932_Russian.bin",
        "name_language": "Russian",
        "id_bin_language": "DragonBallAnime_L2_-196522932_Russian"
      },
      {
        "author": "LMB Studio",
        "link_thumb": "https://live.staticflickr.com/65535/51787834279_4c424fa3a0_o.gif",
        "link_bin": "https://github.com/lmbstudiocontact/mb5_30/raw/main/DragonBallAnime_L2_-196522932_Spanish.bin",
        "name_language": "Spanish",
        "id_bin_language": "DragonBallAnime_L2_-196522932_Spanish"
      }
    ],
    "array_tags": [
      "lmbstudio"
    ],
    "list_album": [
      {
        "id_album": "1464725221",
        "link_thumb": "https://live.staticflickr.com/65535/51787461673_b48c89bc67_o.gif",
        "title": "Dragon Ball Anime_L2"
      }
    ]
  },
  {
    "author": "LMB Studio",
    "link_thumb": "https://live.staticflickr.com/65535/51787461503_704a0e2fcd_o.gif",
    "link_bin": "https://github.com/lmbstudiocontact/mb5_30/raw/main/DragonBallAnime_L2_-196522933.bin",
    "id_bin": "DragonBallAnime_L2_-196522933",
    "list_language": [
      {
        "author": "LMB Studio",
        "link_thumb": "https://live.staticflickr.com/65535/51787211806_d47504e0ef_o.gif",
        "link_bin": "https://github.com/lmbstudiocontact/mb5_30/raw/main/DragonBallAnime_L2_-196522933_English.bin",
        "name_language": "English",
        "id_bin_language": "DragonBallAnime_L2_-196522933_English"
      },
      {
        "author": "LMB Studio",
        "link_thumb": "https://live.staticflickr.com/65535/51788083745_e2bacf5d24_o.gif",
        "link_bin": "https://github.com/lmbstudiocontact/mb5_30/raw/main/DragonBallAnime_L2_-196522933_Portuguese.bin",
        "name_language": "Portuguese",
        "id_bin_language": "DragonBallAnime_L2_-196522933_Portuguese"
      },
      {
        "author": "LMB Studio",
        "link_thumb": "https://live.staticflickr.com/65535/51787211726_29422a0de3_o.gif",
        "link_bin": "https://github.com/lmbstudiocontact/mb5_30/raw/main/DragonBallAnime_L2_-196522933_Russian.bin",
        "name_language": "Russian",
        "id_bin_language": "DragonBallAnime_L2_-196522933_Russian"
      },
      {
        "author": "LMB Studio",
        "link_thumb": "https://live.staticflickr.com/65535/51788083710_473b53be4f_o.gif",
        "link_bin": "https://github.com/lmbstudiocontact/mb5_30/raw/main/DragonBallAnime_L2_-196522933_Spanish.bin",
        "name_language": "Spanish",
        "id_bin_language": "DragonBallAnime_L2_-196522933_Spanish"
      }
    ],
    "array_tags": [
      "lmbstudio"
    ],
    "list_album": [
      {
        "id_album": "1464725221",
        "link_thumb": "https://live.staticflickr.com/65535/51787461503_704a0e2fcd_o.gif",
        "title": "Dragon Ball Anime_L2"
      }
    ]
  },
  {
    "author": "LMB Studio",
    "link_thumb": "https://live.staticflickr.com/65535/51787461248_e5efed2a03_o.gif",
    "link_bin": "https://github.com/lmbstudiocontact/mb5_30/raw/main/DragonBallAnime_L2_-196522934.bin",
    "id_bin": "DragonBallAnime_L2_-196522934",
    "list_language": [
      {
        "author": "LMB Studio",
        "link_thumb": "https://live.staticflickr.com/65535/51786393572_9b58455233_o.gif",
        "link_bin": "https://github.com/lmbstudiocontact/mb5_30/raw/main/DragonBallAnime_L2_-196522934_English.bin",
        "name_language": "English",
        "id_bin_language": "DragonBallAnime_L2_-196522934_English"
      },
      {
        "author": "LMB Studio",
        "link_thumb": "https://live.staticflickr.com/65535/51786393522_58ee883975_o.gif",
        "link_bin": "https://github.com/lmbstudiocontact/mb5_30/raw/main/DragonBallAnime_L2_-196522934_Portuguese.bin",
        "name_language": "Portuguese",
        "id_bin_language": "DragonBallAnime_L2_-196522934_Portuguese"
      },
      {
        "author": "LMB Studio",
        "link_thumb": "https://live.staticflickr.com/65535/51788083585_078bfc6120_o.gif",
        "link_bin": "https://github.com/lmbstudiocontact/mb5_30/raw/main/DragonBallAnime_L2_-196522934_Russian.bin",
        "name_language": "Russian",
        "id_bin_language": "DragonBallAnime_L2_-196522934_Russian"
      },
      {
        "author": "LMB Studio",
        "link_thumb": "https://live.staticflickr.com/65535/51787833919_1ec135690f_o.gif",
        "link_bin": "https://github.com/lmbstudiocontact/mb5_30/raw/main/DragonBallAnime_L2_-196522934_Spanish.bin",
        "name_language": "Spanish",
        "id_bin_language": "DragonBallAnime_L2_-196522934_Spanish"
      }
    ],
    "array_tags": [
      "lmbstudio"
    ],
    "list_album": [
      {
        "id_album": "1464725221",
        "link_thumb": "https://live.staticflickr.com/65535/51787461248_e5efed2a03_o.gif",
        "title": "Dragon Ball Anime_L2"
      }
    ]
  },
  {
    "author": "LMB Studio",
    "link_thumb": "https://live.staticflickr.com/65535/51787461093_fccf5936ff_o.gif",
    "link_bin": "https://github.com/lmbstudiocontact/mb5_30/raw/main/DragonBallAnime_L2_-196522998.bin",
    "id_bin": "DragonBallAnime_L2_-196522998",
    "list_language": [
      {
        "author": "LMB Studio",
        "link_thumb": "https://live.staticflickr.com/65535/51786393382_22ed7d9de5_o.gif",
        "link_bin": "https://github.com/lmbstudiocontact/mb5_30/raw/main/DragonBallAnime_L2_-196522998_English.bin",
        "name_language": "English",
        "id_bin_language": "DragonBallAnime_L2_-196522998_English"
      },
      {
        "author": "LMB Studio",
        "link_thumb": "https://live.staticflickr.com/65535/51787211391_138574fcc0_o.gif",
        "link_bin": "https://github.com/lmbstudiocontact/mb5_30/raw/main/DragonBallAnime_L2_-196522998_Portuguese.bin",
        "name_language": "Portuguese",
        "id_bin_language": "DragonBallAnime_L2_-196522998_Portuguese"
      },
      {
        "author": "LMB Studio",
        "link_thumb": "https://live.staticflickr.com/65535/51787211351_cedbc0de50_o.gif",
        "link_bin": "https://github.com/lmbstudiocontact/mb5_30/raw/main/DragonBallAnime_L2_-196522998_Russian.bin",
        "name_language": "Russian",
        "id_bin_language": "DragonBallAnime_L2_-196522998_Russian"
      },
      {
        "author": "LMB Studio",
        "link_thumb": "https://live.staticflickr.com/65535/51788083405_00b09e1d84_o.gif",
        "link_bin": "https://github.com/lmbstudiocontact/mb5_30/raw/main/DragonBallAnime_L2_-196522998_Spanish.bin",
        "name_language": "Spanish",
        "id_bin_language": "DragonBallAnime_L2_-196522998_Spanish"
      }
    ],
    "array_tags": [
      "lmbstudio"
    ],
    "list_album": [
      {
        "id_album": "1464725221",
        "link_thumb": "https://live.staticflickr.com/65535/51787461093_fccf5936ff_o.gif",
        "title": "Dragon Ball Anime_L2"
      }
    ]
  }
]